{
  "startTimestamp": "1606809781",
  "endTimestamp": "1606896181",
  "region": "NL",
  "batchNum": 1,
  "batchSize": 1,
  "signatureInfos": [
    {
      "verificationKeyVersion": "v12",
      "verificationKeyId": "204",
      "signatureAlgorithm": "1.2.840.10045.4.3.2"
    }
  ],
  "keys": [
    {
      "keyData": "AI8OLr4X3DDKlHdq0zNkRQ==",
      "transmissionRiskLevel": 3,
      "rollingStartIntervalNumber": 2677824,
      "rollingPeriod": 144
    },
    {
      "keyData": "AK4Xn5IVeeTJPs51Kmhfow==",
      "transmissionRiskLevel": 3,
      "rollingStartIntervalNumber": 2677536,
      "rollingPeriod": 144
    },
    {
      "keyData": "As+eunw/x/UDRvxCWkFFrg==",
      "transmissionRiskLevel": 3,
      "rollingStartIntervalNumber": 2676816,
      "rollingPeriod": 144
    },
    {
      "keyData": "AvdNDQgjqAQQLCLI8ZPCaw==",
      "transmissionRiskLevel": 3,
      "rollingStartIntervalNumber": 2677824,
      "rollingPeriod": 144
    },
    {
      "keyData": "BCS+ZLQKnCQLNz7hBcneAw==",
      "transmissionRiskLevel": 2,
      "rollingStartIntervalNumber": 2676960,
      "rollingPeriod": 144
    },
    {
      "keyData": "BR5Qjs6gmv49tGUm9S4V+g==",
      "transmissionRiskLevel": 3,
      "rollingStartIntervalNumber": 2677536,
      "rollingPeriod": 144
    },
    {
      "keyData": "BaOeetZi3WtN/hk+Bcpqiw==",
      "transmissionRiskLevel": 3,
      "rollingStartIntervalNumber": 2677968,
      "rollingPeriod": 144
    },
    {
      "keyData": "CIfMqQNR/Uj1vTgcSiDAow==",
      "transmissionRiskLevel": 3,
      "rollingStartIntervalNumber": 2677680,
      "rollingPeriod": 144
    },
    {
      "keyData": "CPIzR7p7yNHxY+Oq7X72WA==",
      "transmissionRiskLevel": 3,
      "rollingStartIntervalNumber": 2676528,
      "rollingPeriod": 144
    },
    {
      "keyData": "C/i3NTqJQImdo22r3bKj8g==",
      "transmissionRiskLevel": 1,
      "rollingStartIntervalNumber": 2677824,
      "rollingPeriod": 144
    },
    {
      "keyData": "DMRubQGrZV2a8ET+yDK9Iw==",
      "transmissionRiskLevel": 3,
      "rollingStartIntervalNumber": 2677968,
      "rollingPeriod": 144
    },
    {
      "keyData": "D+8ZaeVH87M3aFESmPZojw==",
      "transmissionRiskLevel": 3,
      "rollingStartIntervalNumber": 2677680,
      "rollingPeriod": 144
    },
    {
      "keyData": "EMA/ifehFfm0LTDXKJZXwg==",
      "transmissionRiskLevel": 1,
      "rollingStartIntervalNumber": 2677968,
      "rollingPeriod": 144
    },
    {
      "keyData": "EMN8HDI9bjTBafwf11aY7Q==",
      "transmissionRiskLevel": 3,
      "rollingStartIntervalNumber": 2677680,
      "rollingPeriod": 144
    },
    {
      "keyData": "EduYTFYMyFK3F6l8VcyaFg==",
      "transmissionRiskLevel": 2,
      "rollingStartIntervalNumber": 2677248,
      "rollingPeriod": 144
    },
    {
      "keyData": "EiDfndtV/zBOBKK8x6ES2g==",
      "transmissionRiskLevel": 3,
      "rollingStartIntervalNumber": 2677824,
      "rollingPeriod": 144
    },
    {
      "keyData": "EkAvPnSY+ZBw/QbHVpG/1Q==",
      "transmissionRiskLevel": 2,
      "rollingStartIntervalNumber": 2677398,
      "rollingPeriod": 144
    },
    {
      "keyData": "EuhnOt2jLqM3vJvyKf+xQQ==",
      "transmissionRiskLevel": 3,
      "rollingStartIntervalNumber": 2677104,
      "rollingPeriod": 144
    },
    {
      "keyData": "E1RtE6lp4I93TytVVqRWQw==",
      "transmissionRiskLevel": 2,
      "rollingStartIntervalNumber": 2677824,
      "rollingPeriod": 144
    },
    {
      "keyData": "E5OSlBcd++Qnas6k2wkwNw==",
      "transmissionRiskLevel": 3,
      "rollingStartIntervalNumber": 2677536,
      "rollingPeriod": 144
    },
    {
      "keyData": "E5t5Wc3WFbMTE2JweX/WKw==",
      "transmissionRiskLevel": 3,
      "rollingStartIntervalNumber": 2677542,
      "rollingPeriod": 144
    },
    {
      "keyData": "FFf9kVxUDa4WxZX2VmQ9Cw==",
      "transmissionRiskLevel": 3,
      "rollingStartIntervalNumber": 2677686,
      "rollingPeriod": 144
    },
    {
      "keyData": "FHj+zLJv1AC+phFFAzDA9g==",
      "transmissionRiskLevel": 3,
      "rollingStartIntervalNumber": 2677968,
      "rollingPeriod": 144
    },
    {
      "keyData": "FMGOr8Rr0Lw2882g4mVVxQ==",
      "transmissionRiskLevel": 2,
      "rollingStartIntervalNumber": 2677392,
      "rollingPeriod": 144
    },
    {
      "keyData": "FXT2tAl2YghmglujYj2lVA==",
      "transmissionRiskLevel": 1,
      "rollingStartIntervalNumber": 2677680,
      "rollingPeriod": 144
    },
    {
      "keyData": "FaMBnVSF3sBKBp6FwHvOUA==",
      "transmissionRiskLevel": 3,
      "rollingStartIntervalNumber": 2677536,
      "rollingPeriod": 144
    },
    {
      "keyData": "FoK75LGW1KAd0xFeuJoBYA==",
      "transmissionRiskLevel": 3,
      "rollingStartIntervalNumber": 2677680,
      "rollingPeriod": 144
    },
    {
      "keyData": "F4hAPaqv7R8Zwl2xy3K4Tw==",
      "transmissionRiskLevel": 2,
      "rollingStartIntervalNumber": 2677542,
      "rollingPeriod": 144
    },
    {
      "keyData": "GHfu+3MMdNi6Nrz1Gg97Rw==",
      "transmissionRiskLevel": 2,
      "rollingStartIntervalNumber": 2677254,
      "rollingPeriod": 144
    },
    {
      "keyData": "GePpdyKtIk0LTfoMdiXLcA==",
      "transmissionRiskLevel": 3,
      "rollingStartIntervalNumber": 2677824,
      "rollingPeriod": 144
    },
    {
      "keyData": "Gj2HK4npiJb6/lLREv93fQ==",
      "transmissionRiskLevel": 2,
      "rollingStartIntervalNumber": 2677824,
      "rollingPeriod": 144
    },
    {
      "keyData": "Gup9V0+5gOBQCIf5loiMTg==",
      "transmissionRiskLevel": 3,
      "rollingStartIntervalNumber": 2677680,
      "rollingPeriod": 144
    },
    {
      "keyData": "HS32Bp1kdj8aJlhamKotuw==",
      "transmissionRiskLevel": 3,
      "rollingStartIntervalNumber": 2677680,
      "rollingPeriod": 144
    },
    {
      "keyData": "IQxYtED7uMdVYXO//WGIXQ==",
      "transmissionRiskLevel": 2,
      "rollingStartIntervalNumber": 2677824,
      "rollingPeriod": 144
    },
    {
      "keyData": "IVSTqtS91BUuXJjXbsmxOg==",
      "transmissionRiskLevel": 3,
      "rollingStartIntervalNumber": 2676960,
      "rollingPeriod": 144
    },
    {
      "keyData": "Is5uiu/lkgEalLinew9w/A==",
      "transmissionRiskLevel": 2,
      "rollingStartIntervalNumber": 2676816,
      "rollingPeriod": 144
    },
    {
      "keyData": "JK48+FVXvSwXIwvmtMFuqw==",
      "transmissionRiskLevel": 3,
      "rollingStartIntervalNumber": 2677392,
      "rollingPeriod": 144
    },
    {
      "keyData": "JYcDz9pgrT5nUYWrMI+mBw==",
      "transmissionRiskLevel": 3,
      "rollingStartIntervalNumber": 2677968,
      "rollingPeriod": 144
    },
    {
      "keyData": "JjjJMXcMN7bazoqTi8DyjQ==",
      "transmissionRiskLevel": 3,
      "rollingStartIntervalNumber": 2676240,
      "rollingPeriod": 144
    },
    {
      "keyData": "JmIykXfD/HeVm/qN3TEp7Q==",
      "transmissionRiskLevel": 2,
      "rollingStartIntervalNumber": 2677392,
      "rollingPeriod": 144
    },
    {
      "keyData": "JsDRf9gt+tvrLCD7RG44yg==",
      "transmissionRiskLevel": 2,
      "rollingStartIntervalNumber": 2677824,
      "rollingPeriod": 144
    },
    {
      "keyData": "KI2digwMkZHg7GpgFV01/A==",
      "transmissionRiskLevel": 2,
      "rollingStartIntervalNumber": 2677536,
      "rollingPeriod": 144
    },
    {
      "keyData": "KbcKiQfHBxVSYSN1gQxuqw==",
      "transmissionRiskLevel": 1,
      "rollingStartIntervalNumber": 2677392,
      "rollingPeriod": 144
    },
    {
      "keyData": "KedwZWKN1/vFzFb6iCeXHA==",
      "transmissionRiskLevel": 3,
      "rollingStartIntervalNumber": 2677824,
      "rollingPeriod": 144
    },
    {
      "keyData": "LFR/JQxQjzTmnrA0UPjmlw==",
      "transmissionRiskLevel": 2,
      "rollingStartIntervalNumber": 2676960,
      "rollingPeriod": 144
    },
    {
      "keyData": "LUhgJHLJJFjyxXuxzggL9g==",
      "transmissionRiskLevel": 1,
      "rollingStartIntervalNumber": 2677968,
      "rollingPeriod": 144
    },
    {
      "keyData": "Lc4x0iu0yjCYdjrK3y5JhQ==",
      "transmissionRiskLevel": 2,
      "rollingStartIntervalNumber": 2677824,
      "rollingPeriod": 144
    },
    {
      "keyData": "L+2S9wnLSPOkgFRsd1qxAw==",
      "transmissionRiskLevel": 3,
      "rollingStartIntervalNumber": 2677968,
      "rollingPeriod": 144
    },
    {
      "keyData": "MAggMGGYgg9FOB331mN++w==",
      "transmissionRiskLevel": 3,
      "rollingStartIntervalNumber": 2677398,
      "rollingPeriod": 144
    },
    {
      "keyData": "ML1DsseBG+SSqHTIA9sK5g==",
      "transmissionRiskLevel": 3,
      "rollingStartIntervalNumber": 2677974,
      "rollingPeriod": 144
    },
    {
      "keyData": "MP0/3063smfTBn6rePzz1w==",
      "transmissionRiskLevel": 2,
      "rollingStartIntervalNumber": 2677104,
      "rollingPeriod": 144
    },
    {
      "keyData": "M1nZBuH1LPQImj7MO5scFg==",
      "transmissionRiskLevel": 2,
      "rollingStartIntervalNumber": 2677968,
      "rollingPeriod": 144
    },
    {
      "keyData": "NEvDkCMS5Ng8h+f1Sqd0jw==",
      "transmissionRiskLevel": 2,
      "rollingStartIntervalNumber": 2677254,
      "rollingPeriod": 144
    },
    {
      "keyData": "NYUqR5z6kjvxJ0MmO0HtAQ==",
      "transmissionRiskLevel": 3,
      "rollingStartIntervalNumber": 2677536,
      "rollingPeriod": 144
    },
    {
      "keyData": "NudgwytFjNgaqOn5QHlHIw==",
      "transmissionRiskLevel": 2,
      "rollingStartIntervalNumber": 2677824,
      "rollingPeriod": 144
    },
    {
      "keyData": "N2uRVfyWTTnHs9t0fM/0DA==",
      "transmissionRiskLevel": 2,
      "rollingStartIntervalNumber": 2677968,
      "rollingPeriod": 144
    },
    {
      "keyData": "OSSfs5TCkZ3fSm6hMLSUGg==",
      "transmissionRiskLevel": 3,
      "rollingStartIntervalNumber": 2677968,
      "rollingPeriod": 144
    },
    {
      "keyData": "Ol4AL7RT6CtIDPoNgfYAFg==",
      "transmissionRiskLevel": 2,
      "rollingStartIntervalNumber": 2677824,
      "rollingPeriod": 144
    },
    {
      "keyData": "PFpUls4tiVUbSsEsV5JAfA==",
      "transmissionRiskLevel": 3,
      "rollingStartIntervalNumber": 2677968,
      "rollingPeriod": 144
    },
    {
      "keyData": "PHYaEzc2Yg8N8/nZ4WW0ow==",
      "transmissionRiskLevel": 2,
      "rollingStartIntervalNumber": 2676528,
      "rollingPeriod": 144
    },
    {
      "keyData": "PMOsN7NABx/zU2WRRIO6IQ==",
      "transmissionRiskLevel": 2,
      "rollingStartIntervalNumber": 2677824,
      "rollingPeriod": 144
    },
    {
      "keyData": "QsHdiTwcnQ5+PwdZ5xqp1A==",
      "transmissionRiskLevel": 3,
      "rollingStartIntervalNumber": 2677830,
      "rollingPeriod": 144
    },
    {
      "keyData": "RGk6UzMzbYxCf8tYQBgqDg==",
      "transmissionRiskLevel": 3,
      "rollingStartIntervalNumber": 2677248,
      "rollingPeriod": 144
    },
    {
      "keyData": "RNifWCGpl7qmASpNIqjIOQ==",
      "transmissionRiskLevel": 3,
      "rollingStartIntervalNumber": 2677392,
      "rollingPeriod": 144
    },
    {
      "keyData": "RUr5PvsbP13LDZDTAhOitg==",
      "transmissionRiskLevel": 2,
      "rollingStartIntervalNumber": 2677968,
      "rollingPeriod": 144
    },
    {
      "keyData": "ReAXcSrsmfsHlIHXbArE/A==",
      "transmissionRiskLevel": 3,
      "rollingStartIntervalNumber": 2677536,
      "rollingPeriod": 144
    },
    {
      "keyData": "R53zkRsYBdGT9jX4Coletg==",
      "transmissionRiskLevel": 3,
      "rollingStartIntervalNumber": 2677680,
      "rollingPeriod": 144
    },
    {
      "keyData": "SGx1ogYGq8UhU2514f3l6w==",
      "transmissionRiskLevel": 3,
      "rollingStartIntervalNumber": 2676672,
      "rollingPeriod": 144
    },
    {
      "keyData": "SQMnj9diAuPMr/wQOgJVNA==",
      "transmissionRiskLevel": 3,
      "rollingStartIntervalNumber": 2677824,
      "rollingPeriod": 144
    },
    {
      "keyData": "SStEfNRqUJoECXuNkbaVWQ==",
      "transmissionRiskLevel": 2,
      "rollingStartIntervalNumber": 2677536,
      "rollingPeriod": 144
    },
    {
      "keyData": "SZ3vsWhu3f54eHaZjED3wg==",
      "transmissionRiskLevel": 1,
      "rollingStartIntervalNumber": 2677104,
      "rollingPeriod": 144
    },
    {
      "keyData": "SsNAOhlxuGvlmxFkGKDFtg==",
      "transmissionRiskLevel": 3,
      "rollingStartIntervalNumber": 2677830,
      "rollingPeriod": 144
    },
    {
      "keyData": "S+NRGt+nEnG/5hMv3Ia/Bg==",
      "transmissionRiskLevel": 3,
      "rollingStartIntervalNumber": 2676816,
      "rollingPeriod": 144
    },
    {
      "keyData": "TCZHRK4WkPh8hVMez88/JA==",
      "transmissionRiskLevel": 3,
      "rollingStartIntervalNumber": 2677536,
      "rollingPeriod": 144
    },
    {
      "keyData": "TI6B8mS5udNH0PWRioIJ4w==",
      "transmissionRiskLevel": 3,
      "rollingStartIntervalNumber": 2677104,
      "rollingPeriod": 144
    },
    {
      "keyData": "TJdn6k53HBwyFYm/rudBmg==",
      "transmissionRiskLevel": 1,
      "rollingStartIntervalNumber": 2677968,
      "rollingPeriod": 144
    },
    {
      "keyData": "TY7aWN/h1ca7mxY+vxRCNw==",
      "transmissionRiskLevel": 3,
      "rollingStartIntervalNumber": 2677968,
      "rollingPeriod": 144
    },
    {
      "keyData": "To24vo0rQb094oJcjZNFdA==",
      "transmissionRiskLevel": 1,
      "rollingStartIntervalNumber": 2677536,
      "rollingPeriod": 144
    },
    {
      "keyData": "Tpcs+moVzjrMwhCjOBuTzg==",
      "transmissionRiskLevel": 2,
      "rollingStartIntervalNumber": 2677680,
      "rollingPeriod": 144
    },
    {
      "keyData": "TvFvChIfhLhN2vBYmhBydA==",
      "transmissionRiskLevel": 1,
      "rollingStartIntervalNumber": 2677680,
      "rollingPeriod": 144
    },
    {
      "keyData": "Tz273TmDbgpYtYeqR6eGig==",
      "transmissionRiskLevel": 2,
      "rollingStartIntervalNumber": 2677104,
      "rollingPeriod": 144
    },
    {
      "keyData": "T1TctEkYYpDvzn/FVNncSA==",
      "transmissionRiskLevel": 3,
      "rollingStartIntervalNumber": 2677392,
      "rollingPeriod": 144
    },
    {
      "keyData": "UWhRTj9TENlX5Fm/WHgOcQ==",
      "transmissionRiskLevel": 3,
      "rollingStartIntervalNumber": 2677968,
      "rollingPeriod": 144
    },
    {
      "keyData": "Umr0ZaRyXAbpRsqa+VF1rg==",
      "transmissionRiskLevel": 3,
      "rollingStartIntervalNumber": 2677392,
      "rollingPeriod": 144
    },
    {
      "keyData": "U2lp+Pev7FKBQtZikCuNqw==",
      "transmissionRiskLevel": 3,
      "rollingStartIntervalNumber": 2677824,
      "rollingPeriod": 144
    },
    {
      "keyData": "U6WnxC5bu9LHN0jKeuay5w==",
      "transmissionRiskLevel": 3,
      "rollingStartIntervalNumber": 2677686,
      "rollingPeriod": 144
    },
    {
      "keyData": "U8rRHOzaFckuVk4p5IApHQ==",
      "transmissionRiskLevel": 1,
      "rollingStartIntervalNumber": 2677968,
      "rollingPeriod": 144
    },
    {
      "keyData": "VM0UF/DLhFU/P2JQ42ee7A==",
      "transmissionRiskLevel": 2,
      "rollingStartIntervalNumber": 2677680,
      "rollingPeriod": 144
    },
    {
      "keyData": "VtqEL6vS6ZvW6vgAz3Ihlw==",
      "transmissionRiskLevel": 2,
      "rollingStartIntervalNumber": 2677824,
      "rollingPeriod": 144
    },
    {
      "keyData": "WGAXlgGwykAoNQgC3fAHYw==",
      "transmissionRiskLevel": 3,
      "rollingStartIntervalNumber": 2677974,
      "rollingPeriod": 144
    },
    {
      "keyData": "WkKbR+XZ+if14YhqBhSzoA==",
      "transmissionRiskLevel": 3,
      "rollingStartIntervalNumber": 2677686,
      "rollingPeriod": 144
    },
    {
      "keyData": "XRhi4LL4IemKLBFZr0+iMw==",
      "transmissionRiskLevel": 3,
      "rollingStartIntervalNumber": 2677824,
      "rollingPeriod": 144
    },
    {
      "keyData": "XbFMdMH+KUwz8y+qfFE72g==",
      "transmissionRiskLevel": 1,
      "rollingStartIntervalNumber": 2677824,
      "rollingPeriod": 144
    },
    {
      "keyData": "Xgdhk77hUEgd8i9wRW6LIg==",
      "transmissionRiskLevel": 2,
      "rollingStartIntervalNumber": 2677392,
      "rollingPeriod": 144
    },
    {
      "keyData": "YXhYfhOdtbXP2Pkj6Vw3Fw==",
      "transmissionRiskLevel": 1,
      "rollingStartIntervalNumber": 2677680,
      "rollingPeriod": 144
    },
    {
      "keyData": "YY6ytuN8dq33vbtmlyqHKA==",
      "transmissionRiskLevel": 2,
      "rollingStartIntervalNumber": 2677536,
      "rollingPeriod": 144
    },
    {
      "keyData": "Ylztm8QNVc2n9bKs6BcH6w==",
      "transmissionRiskLevel": 3,
      "rollingStartIntervalNumber": 2677824,
      "rollingPeriod": 144
    },
    {
      "keyData": "ZR97K4LQKx7XfyvojDNvIQ==",
      "transmissionRiskLevel": 3,
      "rollingStartIntervalNumber": 2677968,
      "rollingPeriod": 144
    },
    {
      "keyData": "ZdGdNzRuJuq9r7ieq9fEug==",
      "transmissionRiskLevel": 3,
      "rollingStartIntervalNumber": 2676384,
      "rollingPeriod": 144
    },
    {
      "keyData": "aHrDChyJt6V/GlDMT1Ybdg==",
      "transmissionRiskLevel": 2,
      "rollingStartIntervalNumber": 2677392,
      "rollingPeriod": 144
    },
    {
      "keyData": "ahELE6lvSWgwR9CCGporsQ==",
      "transmissionRiskLevel": 2,
      "rollingStartIntervalNumber": 2677824,
      "rollingPeriod": 144
    },
    {
      "keyData": "ajz1L/FEnKQe9TIwElGHew==",
      "transmissionRiskLevel": 3,
      "rollingStartIntervalNumber": 2677824,
      "rollingPeriod": 144
    },
    {
      "keyData": "atokN1wqXyYAD5jB8MkHjQ==",
      "transmissionRiskLevel": 3,
      "rollingStartIntervalNumber": 2677824,
      "rollingPeriod": 144
    },
    {
      "keyData": "a04CYWOBTDBqX9axKPqPNw==",
      "transmissionRiskLevel": 3,
      "rollingStartIntervalNumber": 2677104,
      "rollingPeriod": 144
    },
    {
      "keyData": "a3tbTYnMX2hX9/k+lRH6mw==",
      "transmissionRiskLevel": 1,
      "rollingStartIntervalNumber": 2677680,
      "rollingPeriod": 144
    },
    {
      "keyData": "b6jbRM3RSsYSQk+OGrgsew==",
      "transmissionRiskLevel": 2,
      "rollingStartIntervalNumber": 2677104,
      "rollingPeriod": 144
    },
    {
      "keyData": "cCcspHQmnafICHcdFBAVnA==",
      "transmissionRiskLevel": 3,
      "rollingStartIntervalNumber": 2677824,
      "rollingPeriod": 144
    },
    {
      "keyData": "cHxgh1rz3GjTKlsalu/1MQ==",
      "transmissionRiskLevel": 3,
      "rollingStartIntervalNumber": 2676672,
      "rollingPeriod": 144
    },
    {
      "keyData": "cJ9kmXD1pm6+BTZAeYhHWw==",
      "transmissionRiskLevel": 3,
      "rollingStartIntervalNumber": 2677686,
      "rollingPeriod": 144
    },
    {
      "keyData": "cc/jcfkUf/pU60GSRpEEUA==",
      "transmissionRiskLevel": 2,
      "rollingStartIntervalNumber": 2677824,
      "rollingPeriod": 144
    },
    {
      "keyData": "c5Bxyy6V3NfvQvgg4GQn/A==",
      "transmissionRiskLevel": 3,
      "rollingStartIntervalNumber": 2677830,
      "rollingPeriod": 144
    },
    {
      "keyData": "dDNJka6+ecSXy7UzK14gyA==",
      "transmissionRiskLevel": 3,
      "rollingStartIntervalNumber": 2677536,
      "rollingPeriod": 144
    },
    {
      "keyData": "dI9q/rfjyL9b5o8d1Yxw0w==",
      "transmissionRiskLevel": 3,
      "rollingStartIntervalNumber": 2677536,
      "rollingPeriod": 144
    },
    {
      "keyData": "dJOvrAZ2KNdL739Z5GFNpg==",
      "transmissionRiskLevel": 3,
      "rollingStartIntervalNumber": 2677680,
      "rollingPeriod": 144
    },
    {
      "keyData": "dWnb7cF6MZRZVKGs7mZV+g==",
      "transmissionRiskLevel": 3,
      "rollingStartIntervalNumber": 2677392,
      "rollingPeriod": 144
    },
    {
      "keyData": "djYjGx0Np4l+ZFs8/LYUEw==",
      "transmissionRiskLevel": 2,
      "rollingStartIntervalNumber": 2677680,
      "rollingPeriod": 144
    },
    {
      "keyData": "doIkEi5Pvr5m3p0E5wi+dw==",
      "transmissionRiskLevel": 2,
      "rollingStartIntervalNumber": 2677536,
      "rollingPeriod": 144
    },
    {
      "keyData": "dossmAZHAI7/Y7VnAW6WEw==",
      "transmissionRiskLevel": 2,
      "rollingStartIntervalNumber": 2677824,
      "rollingPeriod": 144
    },
    {
      "keyData": "drpD6GKd7SUAwZLbBepxkw==",
      "transmissionRiskLevel": 3,
      "rollingStartIntervalNumber": 2676960,
      "rollingPeriod": 144
    },
    {
      "keyData": "d6+qIKiiPCrEMsOLI+8i1w==",
      "transmissionRiskLevel": 3,
      "rollingStartIntervalNumber": 2677824,
      "rollingPeriod": 144
    },
    {
      "keyData": "eHAKlIpnmra/Xj7lHZWpRg==",
      "transmissionRiskLevel": 2,
      "rollingStartIntervalNumber": 2677824,
      "rollingPeriod": 144
    },
    {
      "keyData": "eZWDSYlbExFoACESRqOw0Q==",
      "transmissionRiskLevel": 3,
      "rollingStartIntervalNumber": 2677680,
      "rollingPeriod": 144
    },
    {
      "keyData": "edZtqudEaUtP2VPIuj36+Q==",
      "transmissionRiskLevel": 3,
      "rollingStartIntervalNumber": 2677824,
      "rollingPeriod": 144
    },
    {
      "keyData": "ejslwnkzx29BoC2Uoedfkg==",
      "transmissionRiskLevel": 3,
      "rollingStartIntervalNumber": 2677830,
      "rollingPeriod": 144
    },
    {
      "keyData": "eyLaEeNKuKkXvTxKTgBfuA==",
      "transmissionRiskLevel": 3,
      "rollingStartIntervalNumber": 2677680,
      "rollingPeriod": 144
    },
    {
      "keyData": "e/3dJ6W+IlaCxrYEhWsSdA==",
      "transmissionRiskLevel": 2,
      "rollingStartIntervalNumber": 2677824,
      "rollingPeriod": 144
    },
    {
      "keyData": "fNyq8zauexeb10SYdg090g==",
      "transmissionRiskLevel": 1,
      "rollingStartIntervalNumber": 2677968,
      "rollingPeriod": 144
    },
    {
      "keyData": "faEoubbtweNqmPDB7q9RyQ==",
      "transmissionRiskLevel": 3,
      "rollingStartIntervalNumber": 2676672,
      "rollingPeriod": 144
    },
    {
      "keyData": "gHsOkaSSqul4cOcjuAeSfw==",
      "transmissionRiskLevel": 3,
      "rollingStartIntervalNumber": 2677536,
      "rollingPeriod": 144
    },
    {
      "keyData": "gbItc3kwjNWFTGimZXkC4A==",
      "transmissionRiskLevel": 3,
      "rollingStartIntervalNumber": 2677680,
      "rollingPeriod": 144
    },
    {
      "keyData": "g4MsMwhwur1TSdBDnJH9gw==",
      "transmissionRiskLevel": 3,
      "rollingStartIntervalNumber": 2677536,
      "rollingPeriod": 144
    },
    {
      "keyData": "g8t/S3j4Medem2Zt84+hVQ==",
      "transmissionRiskLevel": 3,
      "rollingStartIntervalNumber": 2677968,
      "rollingPeriod": 144
    },
    {
      "keyData": "hAueRrZBf4I7Se8YRg2c2w==",
      "transmissionRiskLevel": 2,
      "rollingStartIntervalNumber": 2677680,
      "rollingPeriod": 144
    },
    {
      "keyData": "hGc/ZmhzgCeR9ZuXXLpDYw==",
      "transmissionRiskLevel": 2,
      "rollingStartIntervalNumber": 2677824,
      "rollingPeriod": 144
    },
    {
      "keyData": "hLOhxu5PXpIzVV9n2JFsNg==",
      "transmissionRiskLevel": 1,
      "rollingStartIntervalNumber": 2677536,
      "rollingPeriod": 144
    },
    {
      "keyData": "h5BWcUhu+SCMQoIpdPmEHA==",
      "transmissionRiskLevel": 3,
      "rollingStartIntervalNumber": 2677680,
      "rollingPeriod": 144
    },
    {
      "keyData": "h/OzvlTuosrWp1HS7K05mw==",
      "transmissionRiskLevel": 3,
      "rollingStartIntervalNumber": 2677968,
      "rollingPeriod": 144
    },
    {
      "keyData": "h/2cyi+2UX2p39TVrwvPjQ==",
      "transmissionRiskLevel": 2,
      "rollingStartIntervalNumber": 2677968,
      "rollingPeriod": 144
    },
    {
      "keyData": "iAS/e281NFXtBM/TODcNuA==",
      "transmissionRiskLevel": 2,
      "rollingStartIntervalNumber": 2677824,
      "rollingPeriod": 144
    },
    {
      "keyData": "iLSgTHAh6TztklGUHyM9qw==",
      "transmissionRiskLevel": 3,
      "rollingStartIntervalNumber": 2677968,
      "rollingPeriod": 144
    },
    {
      "keyData": "iV3oSNZ7WDTa0Q7Tex/cFA==",
      "transmissionRiskLevel": 2,
      "rollingStartIntervalNumber": 2677248,
      "rollingPeriod": 144
    },
    {
      "keyData": "imOnz1VzQ0XOPcZnGV+2cA==",
      "transmissionRiskLevel": 2,
      "rollingStartIntervalNumber": 2677968,
      "rollingPeriod": 144
    },
    {
      "keyData": "iu5PexOKuxuIolZciAIuRg==",
      "transmissionRiskLevel": 3,
      "rollingStartIntervalNumber": 2677392,
      "rollingPeriod": 144
    },
    {
      "keyData": "jgvfsvQS8eMsRlsaHezJTQ==",
      "transmissionRiskLevel": 3,
      "rollingStartIntervalNumber": 2676816,
      "rollingPeriod": 144
    },
    {
      "keyData": "jlsfm7RpM4ymEiojXBhxXQ==",
      "transmissionRiskLevel": 3,
      "rollingStartIntervalNumber": 2677968,
      "rollingPeriod": 144
    },
    {
      "keyData": "jtZIj5P9uMCvVgJVs9dLSA==",
      "transmissionRiskLevel": 3,
      "rollingStartIntervalNumber": 2677824,
      "rollingPeriod": 144
    },
    {
      "keyData": "jtiSo+rNgFR9QU8He0KOhg==",
      "transmissionRiskLevel": 2,
      "rollingStartIntervalNumber": 2677824,
      "rollingPeriod": 144
    },
    {
      "keyData": "jybA213YMwhfIJtZJ1kW3g==",
      "transmissionRiskLevel": 3,
      "rollingStartIntervalNumber": 2677968,
      "rollingPeriod": 144
    },
    {
      "keyData": "j0O2dzv9BAeLNUX379E+Ag==",
      "transmissionRiskLevel": 3,
      "rollingStartIntervalNumber": 2677824,
      "rollingPeriod": 144
    },
    {
      "keyData": "j3WkMWStPveKLR4dHmnJtw==",
      "transmissionRiskLevel": 2,
      "rollingStartIntervalNumber": 2677104,
      "rollingPeriod": 144
    },
    {
      "keyData": "kWVL73EMQg9sUbzf5cMz2g==",
      "transmissionRiskLevel": 3,
      "rollingStartIntervalNumber": 2677968,
      "rollingPeriod": 144
    },
    {
      "keyData": "kZDWpJLI8a9kN5bFGCjhHw==",
      "transmissionRiskLevel": 3,
      "rollingStartIntervalNumber": 2677974,
      "rollingPeriod": 144
    },
    {
      "keyData": "kcbxzCkf8Pm42oTdkIM0Ng==",
      "transmissionRiskLevel": 3,
      "rollingStartIntervalNumber": 2677248,
      "rollingPeriod": 144
    },
    {
      "keyData": "klD48o+onW2ikFhEjVJtlw==",
      "transmissionRiskLevel": 3,
      "rollingStartIntervalNumber": 2676528,
      "rollingPeriod": 144
    },
    {
      "keyData": "klPHsFGZtZp+7xVLB5hgyQ==",
      "transmissionRiskLevel": 1,
      "rollingStartIntervalNumber": 2677968,
      "rollingPeriod": 144
    },
    {
      "keyData": "kw5vnm22pUYbx3LplTObfg==",
      "transmissionRiskLevel": 3,
      "rollingStartIntervalNumber": 2677968,
      "rollingPeriod": 144
    },
    {
      "keyData": "kyToFXVeHrkPc+em8mfoKQ==",
      "transmissionRiskLevel": 3,
      "rollingStartIntervalNumber": 2677968,
      "rollingPeriod": 144
    },
    {
      "keyData": "k27cGizDfK+cysVSC25qhg==",
      "transmissionRiskLevel": 3,
      "rollingStartIntervalNumber": 2677680,
      "rollingPeriod": 144
    },
    {
      "keyData": "k59d4hwwnByby/3DFrrCrw==",
      "transmissionRiskLevel": 2,
      "rollingStartIntervalNumber": 2677968,
      "rollingPeriod": 144
    },
    {
      "keyData": "k71WlQf66foJTMnZKLvaeA==",
      "transmissionRiskLevel": 3,
      "rollingStartIntervalNumber": 2677542,
      "rollingPeriod": 144
    },
    {
      "keyData": "lJEsg8OMNTx3ugMVaq8pAA==",
      "transmissionRiskLevel": 2,
      "rollingStartIntervalNumber": 2676672,
      "rollingPeriod": 144
    },
    {
      "keyData": "lrp57vHa2J76+MXoJQ31KQ==",
      "transmissionRiskLevel": 3,
      "rollingStartIntervalNumber": 2677680,
      "rollingPeriod": 144
    },
    {
      "keyData": "lwR0rkKwvg14lZTfw59B6A==",
      "transmissionRiskLevel": 2,
      "rollingStartIntervalNumber": 2677104,
      "rollingPeriod": 144
    },
    {
      "keyData": "mOgyz18co1yvBozn90YF3g==",
      "transmissionRiskLevel": 3,
      "rollingStartIntervalNumber": 2677968,
      "rollingPeriod": 144
    },
    {
      "keyData": "moYlm/MuO3+SiSYYSLdSsQ==",
      "transmissionRiskLevel": 2,
      "rollingStartIntervalNumber": 2677824,
      "rollingPeriod": 144
    },
    {
      "keyData": "mq6Hhgdr4c4RPij1zQ4KPA==",
      "transmissionRiskLevel": 3,
      "rollingStartIntervalNumber": 2677248,
      "rollingPeriod": 144
    },
    {
      "keyData": "m3V0W6ixCIn+ACY59EQRcg==",
      "transmissionRiskLevel": 2,
      "rollingStartIntervalNumber": 2677104,
      "rollingPeriod": 144
    },
    {
      "keyData": "m99EFer+BvVnho7M0grpDw==",
      "transmissionRiskLevel": 2,
      "rollingStartIntervalNumber": 2677248,
      "rollingPeriod": 144
    },
    {
      "keyData": "nH55hiSnc5v6idrlN9CC2g==",
      "transmissionRiskLevel": 3,
      "rollingStartIntervalNumber": 2677536,
      "rollingPeriod": 144
    },
    {
      "keyData": "oUK9/dOzpcO7ZXFBEFrstA==",
      "transmissionRiskLevel": 2,
      "rollingStartIntervalNumber": 2676384,
      "rollingPeriod": 144
    },
    {
      "keyData": "od5KqW7TEOfjihPez3YeBQ==",
      "transmissionRiskLevel": 3,
      "rollingStartIntervalNumber": 2677830,
      "rollingPeriod": 144
    },
    {
      "keyData": "oqez6Uj3dizR9EC30ZXfZA==",
      "transmissionRiskLevel": 3,
      "rollingStartIntervalNumber": 2677398,
      "rollingPeriod": 144
    },
    {
      "keyData": "o0IEZfhoP+mDJ1tt7DxC5w==",
      "transmissionRiskLevel": 3,
      "rollingStartIntervalNumber": 2677248,
      "rollingPeriod": 144
    },
    {
      "keyData": "o/TnTjc3tzZBivLGbDf98g==",
      "transmissionRiskLevel": 3,
      "rollingStartIntervalNumber": 2677968,
      "rollingPeriod": 144
    },
    {
      "keyData": "pUjh6hZsOg3dwk+Amuh+mA==",
      "transmissionRiskLevel": 3,
      "rollingStartIntervalNumber": 2677968,
      "rollingPeriod": 144
    },
    {
      "keyData": "p5EQL58tUC1aodM/VDYvow==",
      "transmissionRiskLevel": 3,
      "rollingStartIntervalNumber": 2677968,
      "rollingPeriod": 144
    },
    {
      "keyData": "qLYvvmbu7YZYiJ2mmRURwA==",
      "transmissionRiskLevel": 2,
      "rollingStartIntervalNumber": 2677536,
      "rollingPeriod": 144
    },
    {
      "keyData": "qN8FfG5ybeCWtRCt5OaI7w==",
      "transmissionRiskLevel": 3,
      "rollingStartIntervalNumber": 2677968,
      "rollingPeriod": 144
    },
    {
      "keyData": "qOTA8y7S8+WruEdi0s/9uw==",
      "transmissionRiskLevel": 1,
      "rollingStartIntervalNumber": 2677248,
      "rollingPeriod": 144
    },
    {
      "keyData": "qOhRu98/U29+W9f8JCNyww==",
      "transmissionRiskLevel": 3,
      "rollingStartIntervalNumber": 2677248,
      "rollingPeriod": 144
    },
    {
      "keyData": "qWE6IlUuAIrL/o3Fh3iKAg==",
      "transmissionRiskLevel": 1,
      "rollingStartIntervalNumber": 2677968,
      "rollingPeriod": 144
    },
    {
      "keyData": "qdX0D496i68Lod07l5H+ig==",
      "transmissionRiskLevel": 3,
      "rollingStartIntervalNumber": 2677974,
      "rollingPeriod": 144
    },
    {
      "keyData": "qt8hG20c3VGj0yrz/XZXLw==",
      "transmissionRiskLevel": 3,
      "rollingStartIntervalNumber": 2677968,
      "rollingPeriod": 144
    },
    {
      "keyData": "q4ras1ABeNUagauAEgS5uA==",
      "transmissionRiskLevel": 3,
      "rollingStartIntervalNumber": 2676816,
      "rollingPeriod": 144
    },
    {
      "keyData": "rDsmcnrDLH2hJJvhh1sHEg==",
      "transmissionRiskLevel": 3,
      "rollingStartIntervalNumber": 2677824,
      "rollingPeriod": 144
    },
    {
      "keyData": "ra6S8P1mZP9bmf5ghF+tIA==",
      "transmissionRiskLevel": 2,
      "rollingStartIntervalNumber": 2677536,
      "rollingPeriod": 144
    },
    {
      "keyData": "r4FbvccIqhfzwSDm/42SNQ==",
      "transmissionRiskLevel": 3,
      "rollingStartIntervalNumber": 2677968,
      "rollingPeriod": 144
    },
    {
      "keyData": "sJqzjzYEgCQFBqTeq3AnYQ==",
      "transmissionRiskLevel": 2,
      "rollingStartIntervalNumber": 2677248,
      "rollingPeriod": 144
    },
    {
      "keyData": "sk8YWOp/5zava5HpN4i7mQ==",
      "transmissionRiskLevel": 2,
      "rollingStartIntervalNumber": 2677824,
      "rollingPeriod": 144
    },
    {
      "keyData": "srqc6nttxfUHLX7ovoZ1Lg==",
      "transmissionRiskLevel": 3,
      "rollingStartIntervalNumber": 2677104,
      "rollingPeriod": 144
    },
    {
      "keyData": "s5JTF62J4N40w/aYFZn+ww==",
      "transmissionRiskLevel": 3,
      "rollingStartIntervalNumber": 2677680,
      "rollingPeriod": 144
    },
    {
      "keyData": "usMpJHVrUjzwBXsshVXZLA==",
      "transmissionRiskLevel": 2,
      "rollingStartIntervalNumber": 2677536,
      "rollingPeriod": 144
    },
    {
      "keyData": "uu2lZv2j0v2LkzApvKVnbQ==",
      "transmissionRiskLevel": 2,
      "rollingStartIntervalNumber": 2677536,
      "rollingPeriod": 144
    },
    {
      "keyData": "uyqoWfexUUWIBrEi4aae1Q==",
      "transmissionRiskLevel": 3,
      "rollingStartIntervalNumber": 2677248,
      "rollingPeriod": 144
    },
    {
      "keyData": "vBsxqTurTCE9fqGuiPuufA==",
      "transmissionRiskLevel": 2,
      "rollingStartIntervalNumber": 2677392,
      "rollingPeriod": 144
    },
    {
      "keyData": "vaGsVDtzR1BcdN3lPQ2W9Q==",
      "transmissionRiskLevel": 3,
      "rollingStartIntervalNumber": 2676960,
      "rollingPeriod": 144
    },
    {
      "keyData": "vaY1aWPc6vQETaq36OZa+g==",
      "transmissionRiskLevel": 1,
      "rollingStartIntervalNumber": 2677680,
      "rollingPeriod": 144
    },
    {
      "keyData": "voo3AxzyBfUY6JIX+bZLog==",
      "transmissionRiskLevel": 3,
      "rollingStartIntervalNumber": 2677968,
      "rollingPeriod": 144
    },
    {
      "keyData": "v3IsvgfhwdGY2ti4MLqaDw==",
      "transmissionRiskLevel": 3,
      "rollingStartIntervalNumber": 2677542,
      "rollingPeriod": 144
    },
    {
      "keyData": "v4/KNn0m4qALfVnWdhUQTw==",
      "transmissionRiskLevel": 2,
      "rollingStartIntervalNumber": 2677542,
      "rollingPeriod": 144
    },
    {
      "keyData": "wDDxTDitps8y2Hjcq6BlUg==",
      "transmissionRiskLevel": 3,
      "rollingStartIntervalNumber": 2677536,
      "rollingPeriod": 144
    },
    {
      "keyData": "wKLQrIIvBlQ6STOKOq4HDQ==",
      "transmissionRiskLevel": 3,
      "rollingStartIntervalNumber": 2677824,
      "rollingPeriod": 144
    },
    {
      "keyData": "wZwo2vLVxt2Lz/Y9p+i/WQ==",
      "transmissionRiskLevel": 1,
      "rollingStartIntervalNumber": 2677392,
      "rollingPeriod": 144
    },
    {
      "keyData": "wiWkRV0FYBmJI2OLio4OYA==",
      "transmissionRiskLevel": 3,
      "rollingStartIntervalNumber": 2677680,
      "rollingPeriod": 144
    },
    {
      "keyData": "w0JBocwocEejPEhQocXKoQ==",
      "transmissionRiskLevel": 3,
      "rollingStartIntervalNumber": 2677248,
      "rollingPeriod": 144
    },
    {
      "keyData": "xA5XS9ge8/De50u63cIM7Q==",
      "transmissionRiskLevel": 3,
      "rollingStartIntervalNumber": 2677968,
      "rollingPeriod": 144
    },
    {
      "keyData": "xHhxyMtoMnvVQBMWuaKItA==",
      "transmissionRiskLevel": 3,
      "rollingStartIntervalNumber": 2677536,
      "rollingPeriod": 144
    },
    {
      "keyData": "xIRK+1o2NHrNzgoxbK38pw==",
      "transmissionRiskLevel": 1,
      "rollingStartIntervalNumber": 2677824,
      "rollingPeriod": 144
    },
    {
      "keyData": "xt8eYWpK2z1z7Fpw6zLwZQ==",
      "transmissionRiskLevel": 3,
      "rollingStartIntervalNumber": 2677824,
      "rollingPeriod": 144
    },
    {
      "keyData": "xzfd7JIuqLADAseTxZXa9w==",
      "transmissionRiskLevel": 1,
      "rollingStartIntervalNumber": 2677392,
      "rollingPeriod": 144
    },
    {
      "keyData": "xzscDrysIzhx+T9xlEbvPg==",
      "transmissionRiskLevel": 2,
      "rollingStartIntervalNumber": 2676960,
      "rollingPeriod": 144
    },
    {
      "keyData": "yV0CjBT2vWPpIVNAd+l8UQ==",
      "transmissionRiskLevel": 2,
      "rollingStartIntervalNumber": 2677824,
      "rollingPeriod": 144
    },
    {
      "keyData": "y6pArNE5Y4Q8COqDozWjVQ==",
      "transmissionRiskLevel": 3,
      "rollingStartIntervalNumber": 2677824,
      "rollingPeriod": 144
    },
    {
      "keyData": "zCipvLv8c6u10aTe1Ck7Sw==",
      "transmissionRiskLevel": 3,
      "rollingStartIntervalNumber": 2677680,
      "rollingPeriod": 144
    },
    {
      "keyData": "zNTVVPdk7/IhnK08MnXajw==",
      "transmissionRiskLevel": 1,
      "rollingStartIntervalNumber": 2677968,
      "rollingPeriod": 144
    },
    {
      "keyData": "zNjSkAv9y0llhepEWIuMrw==",
      "transmissionRiskLevel": 3,
      "rollingStartIntervalNumber": 2677968,
      "rollingPeriod": 144
    },
    {
      "keyData": "zYE57A88mP5M2kcR7ZDp8g==",
      "transmissionRiskLevel": 3,
      "rollingStartIntervalNumber": 2677680,
      "rollingPeriod": 144
    },
    {
      "keyData": "zq/duxPj5ZX/WVVajxc1wQ==",
      "transmissionRiskLevel": 3,
      "rollingStartIntervalNumber": 2677974,
      "rollingPeriod": 144
    },
    {
      "keyData": "zye5FEPJiG2eO+PIA91bGQ==",
      "transmissionRiskLevel": 3,
      "rollingStartIntervalNumber": 2677536,
      "rollingPeriod": 144
    },
    {
      "keyData": "0AfS//r5FETvYIQgmvT7kw==",
      "transmissionRiskLevel": 2,
      "rollingStartIntervalNumber": 2677248,
      "rollingPeriod": 144
    },
    {
      "keyData": "0REhvXM9tDz3hiLQCDWYWA==",
      "transmissionRiskLevel": 3,
      "rollingStartIntervalNumber": 2677536,
      "rollingPeriod": 144
    },
    {
      "keyData": "0dIm5H8UT66qkshqyEs5jw==",
      "transmissionRiskLevel": 3,
      "rollingStartIntervalNumber": 2677968,
      "rollingPeriod": 144
    },
    {
      "keyData": "071gk++24+OwgBenEzN7sw==",
      "transmissionRiskLevel": 3,
      "rollingStartIntervalNumber": 2677824,
      "rollingPeriod": 144
    },
    {
      "keyData": "1SPo5fxyTTZhfJwDT3UeMQ==",
      "transmissionRiskLevel": 3,
      "rollingStartIntervalNumber": 2677542,
      "rollingPeriod": 144
    },
    {
      "keyData": "1c35IIOeibfrQGofz4TVig==",
      "transmissionRiskLevel": 3,
      "rollingStartIntervalNumber": 2676528,
      "rollingPeriod": 144
    },
    {
      "keyData": "1pjABhg2DM8Eh6tl+82fMw==",
      "transmissionRiskLevel": 3,
      "rollingStartIntervalNumber": 2677392,
      "rollingPeriod": 144
    },
    {
      "keyData": "2C9KrO5RysPZt9jsYY8o1w==",
      "transmissionRiskLevel": 2,
      "rollingStartIntervalNumber": 2677680,
      "rollingPeriod": 144
    },
    {
      "keyData": "2WI92eEYZ3FTt2AJnD91tg==",
      "transmissionRiskLevel": 2,
      "rollingStartIntervalNumber": 2677968,
      "rollingPeriod": 144
    },
    {
      "keyData": "2aeZcSnSn2pUC2r2N7AaDg==",
      "transmissionRiskLevel": 3,
      "rollingStartIntervalNumber": 2677680,
      "rollingPeriod": 144
    },
    {
      "keyData": "3BXYxQgat0epNf8QMQvnIg==",
      "transmissionRiskLevel": 2,
      "rollingStartIntervalNumber": 2677680,
      "rollingPeriod": 144
    },
    {
      "keyData": "3QuBNG92X8dJ9I+PAXNpQg==",
      "transmissionRiskLevel": 3,
      "rollingStartIntervalNumber": 2677248,
      "rollingPeriod": 144
    },
    {
      "keyData": "3dVehSx7iqpomKvzPBuVYw==",
      "transmissionRiskLevel": 2,
      "rollingStartIntervalNumber": 2676384,
      "rollingPeriod": 144
    },
    {
      "keyData": "3jrlf7nEhfaC9VymgcQSRg==",
      "transmissionRiskLevel": 2,
      "rollingStartIntervalNumber": 2677824,
      "rollingPeriod": 144
    },
    {
      "keyData": "3k0oamZaLuixirSh4qXmCQ==",
      "transmissionRiskLevel": 3,
      "rollingStartIntervalNumber": 2677392,
      "rollingPeriod": 144
    },
    {
      "keyData": "3ws1gLtlK5WnuvKfIAclXQ==",
      "transmissionRiskLevel": 1,
      "rollingStartIntervalNumber": 2677824,
      "rollingPeriod": 144
    },
    {
      "keyData": "3yKGupZtSFFnLEvcfxGKOA==",
      "transmissionRiskLevel": 3,
      "rollingStartIntervalNumber": 2677392,
      "rollingPeriod": 144
    },
    {
      "keyData": "39TWpI6ct0FstOeLU75kHQ==",
      "transmissionRiskLevel": 3,
      "rollingStartIntervalNumber": 2677968,
      "rollingPeriod": 144
    },
    {
      "keyData": "3/YlO8oaOIyUJcnrwFipdg==",
      "transmissionRiskLevel": 3,
      "rollingStartIntervalNumber": 2677680,
      "rollingPeriod": 144
    },
    {
      "keyData": "3/de56wVrB9ngWe7KcoMBg==",
      "transmissionRiskLevel": 3,
      "rollingStartIntervalNumber": 2677686,
      "rollingPeriod": 144
    },
    {
      "keyData": "4CpC/BktHQcZ5GkvQ+nLTg==",
      "transmissionRiskLevel": 3,
      "rollingStartIntervalNumber": 2677968,
      "rollingPeriod": 144
    },
    {
      "keyData": "4bGzGhxepnstoEN34Rso4Q==",
      "transmissionRiskLevel": 1,
      "rollingStartIntervalNumber": 2677824,
      "rollingPeriod": 144
    },
    {
      "keyData": "4xzdAloYL7Wh+hx9d4XtBw==",
      "transmissionRiskLevel": 1,
      "rollingStartIntervalNumber": 2677968,
      "rollingPeriod": 144
    },
    {
      "keyData": "48wffEijWX2gXsOjLU/yRQ==",
      "transmissionRiskLevel": 1,
      "rollingStartIntervalNumber": 2677536,
      "rollingPeriod": 144
    },
    {
      "keyData": "49tFtRML2jbHVaEPB2wgqw==",
      "transmissionRiskLevel": 3,
      "rollingStartIntervalNumber": 2677824,
      "rollingPeriod": 144
    },
    {
      "keyData": "5BG1R32rjKNUtvnDNnd/Ig==",
      "transmissionRiskLevel": 3,
      "rollingStartIntervalNumber": 2677968,
      "rollingPeriod": 144
    },
    {
      "keyData": "5Fo1R2uc/ggtv7SDNbNJxQ==",
      "transmissionRiskLevel": 3,
      "rollingStartIntervalNumber": 2677968,
      "rollingPeriod": 144
    },
    {
      "keyData": "5JXNynhNARKQ9dDXjK3gKg==",
      "transmissionRiskLevel": 2,
      "rollingStartIntervalNumber": 2677824,
      "rollingPeriod": 144
    },
    {
      "keyData": "5ZE1ZfQA4Mb0+bPaCKQ8uw==",
      "transmissionRiskLevel": 1,
      "rollingStartIntervalNumber": 2677968,
      "rollingPeriod": 144
    },
    {
      "keyData": "5dbJC08J0fdLDPzVZnNIHw==",
      "transmissionRiskLevel": 2,
      "rollingStartIntervalNumber": 2677680,
      "rollingPeriod": 144
    },
    {
      "keyData": "5gWSJRhRvx5TyMOet0rlrA==",
      "transmissionRiskLevel": 3,
      "rollingStartIntervalNumber": 2677968,
      "rollingPeriod": 144
    },
    {
      "keyData": "5sTcRL4mJ3XBp6y2d73FIw==",
      "transmissionRiskLevel": 3,
      "rollingStartIntervalNumber": 2677830,
      "rollingPeriod": 144
    },
    {
      "keyData": "6ITMvoWqhZIIhUS4VeG7Eg==",
      "transmissionRiskLevel": 3,
      "rollingStartIntervalNumber": 2677686,
      "rollingPeriod": 144
    },
    {
      "keyData": "6Ia8QvUYyg89jk0gqLTzDg==",
      "transmissionRiskLevel": 2,
      "rollingStartIntervalNumber": 2676816,
      "rollingPeriod": 144
    },
    {
      "keyData": "6UNQ9gVu9nn8QX5XIs3kTw==",
      "transmissionRiskLevel": 2,
      "rollingStartIntervalNumber": 2677248,
      "rollingPeriod": 144
    },
    {
      "keyData": "6UPGclDz8EXmxXerVll99Q==",
      "transmissionRiskLevel": 3,
      "rollingStartIntervalNumber": 2676960,
      "rollingPeriod": 144
    },
    {
      "keyData": "6U0wAUtIHKAvqhOHuDUXqQ==",
      "transmissionRiskLevel": 3,
      "rollingStartIntervalNumber": 2677824,
      "rollingPeriod": 144
    },
    {
      "keyData": "6VH7dJ/3oKU0BNxmqgGwyQ==",
      "transmissionRiskLevel": 3,
      "rollingStartIntervalNumber": 2677680,
      "rollingPeriod": 144
    },
    {
      "keyData": "7Y6C0bynlL7EMMPy3XAuHQ==",
      "transmissionRiskLevel": 2,
      "rollingStartIntervalNumber": 2677392,
      "rollingPeriod": 144
    },
    {
      "keyData": "704PYFMucMDN16eAsuM/Gg==",
      "transmissionRiskLevel": 2,
      "rollingStartIntervalNumber": 2677536,
      "rollingPeriod": 144
    },
    {
      "keyData": "8Xea/P/QmJQ3tgLyApm3jg==",
      "transmissionRiskLevel": 3,
      "rollingStartIntervalNumber": 2677536,
      "rollingPeriod": 144
    },
    {
      "keyData": "8j2mp+CpudkRV96dTTJIyA==",
      "transmissionRiskLevel": 2,
      "rollingStartIntervalNumber": 2677968,
      "rollingPeriod": 144
    },
    {
      "keyData": "8m5PrlUkNfav1VV1INAtaA==",
      "transmissionRiskLevel": 3,
      "rollingStartIntervalNumber": 2677392,
      "rollingPeriod": 144
    },
    {
      "keyData": "8wdvxKV1wdYZwfroh9TB+A==",
      "transmissionRiskLevel": 3,
      "rollingStartIntervalNumber": 2677824,
      "rollingPeriod": 144
    },
    {
      "keyData": "8056dFRv8oxbReYIJVMBjQ==",
      "transmissionRiskLevel": 3,
      "rollingStartIntervalNumber": 2677974,
      "rollingPeriod": 144
    },
    {
      "keyData": "88J4y44KHTltyXKojR5n4w==",
      "transmissionRiskLevel": 2,
      "rollingStartIntervalNumber": 2677392,
      "rollingPeriod": 144
    },
    {
      "keyData": "9VsUPdBvcOHN6g7CTtLZ+w==",
      "transmissionRiskLevel": 1,
      "rollingStartIntervalNumber": 2677536,
      "rollingPeriod": 144
    },
    {
      "keyData": "9ffKzIGeIpLz1UYxGMnNqg==",
      "transmissionRiskLevel": 1,
      "rollingStartIntervalNumber": 2677680,
      "rollingPeriod": 144
    },
    {
      "keyData": "9fsIwv/S/OdJc85WMhy1Ug==",
      "transmissionRiskLevel": 3,
      "rollingStartIntervalNumber": 2677968,
      "rollingPeriod": 144
    },
    {
      "keyData": "9nSUDkWeuex9UqsB4NLyhA==",
      "transmissionRiskLevel": 3,
      "rollingStartIntervalNumber": 2677680,
      "rollingPeriod": 144
    },
    {
      "keyData": "968C3n+lzlhucMNa1RS7Ow==",
      "transmissionRiskLevel": 3,
      "rollingStartIntervalNumber": 2677104,
      "rollingPeriod": 144
    },
    {
      "keyData": "+GaIQCzNirWj6wDhNEDZYQ==",
      "transmissionRiskLevel": 3,
      "rollingStartIntervalNumber": 2677680,
      "rollingPeriod": 144
    },
    {
      "keyData": "+PpIWucUBUS7V00GiDVE5Q==",
      "transmissionRiskLevel": 2,
      "rollingStartIntervalNumber": 2677248,
      "rollingPeriod": 144
    },
    {
      "keyData": "+fqlyB86SJ15GlhatQcblg==",
      "transmissionRiskLevel": 1,
      "rollingStartIntervalNumber": 2677824,
      "rollingPeriod": 144
    },
    {
      "keyData": "+p6wnFjW4pOXi6KUHTEeiQ==",
      "transmissionRiskLevel": 2,
      "rollingStartIntervalNumber": 2677824,
      "rollingPeriod": 144
    },
    {
      "keyData": "+rHm5KU4aHKC6Yc+E/NuaA==",
      "transmissionRiskLevel": 3,
      "rollingStartIntervalNumber": 2677974,
      "rollingPeriod": 144
    },
    {
      "keyData": "+rhLYoYaYCmuV/m+vS1Onw==",
      "transmissionRiskLevel": 2,
      "rollingStartIntervalNumber": 2677398,
      "rollingPeriod": 144
    },
    {
      "keyData": "+wJ/Upk13UCgUARPrE25Iw==",
      "transmissionRiskLevel": 1,
      "rollingStartIntervalNumber": 2677824,
      "rollingPeriod": 144
    },
    {
      "keyData": "+3MuhIaCvl98eRuv2/mVsg==",
      "transmissionRiskLevel": 2,
      "rollingStartIntervalNumber": 2677824,
      "rollingPeriod": 144
    },
    {
      "keyData": "/F4QGQMZ2jWlk+GrVcG12w==",
      "transmissionRiskLevel": 3,
      "rollingStartIntervalNumber": 2676672,
      "rollingPeriod": 144
    },
    {
      "keyData": "/W3+pFXBKL3cHPCCxxe/tw==",
      "transmissionRiskLevel": 3,
      "rollingStartIntervalNumber": 2676960,
      "rollingPeriod": 144
    },
    {
      "keyData": "/lIeq9lc2CFhqUIUqaMSZg==",
      "transmissionRiskLevel": 2,
      "rollingStartIntervalNumber": 2677968,
      "rollingPeriod": 144
    },
    {
      "keyData": "/sbata7tNyfIYfVEDgTtgw==",
      "transmissionRiskLevel": 3,
      "rollingStartIntervalNumber": 2677392,
      "rollingPeriod": 144
    },
    {
      "keyData": "/23kGwg7jCAs97uGxnxvAA==",
      "transmissionRiskLevel": 3,
      "rollingStartIntervalNumber": 2677968,
      "rollingPeriod": 144
    }
  ]
}