{
  "startTimestamp": "1605996180",
  "endTimestamp": "1606082580",
  "region": "NL",
  "batchNum": 1,
  "batchSize": 1,
  "signatureInfos": [
    {
      "verificationKeyVersion": "v12",
      "verificationKeyId": "204",
      "signatureAlgorithm": "1.2.840.10045.4.3.2"
    }
  ],
  "keys": [
    {
      "keyData": "AOCc8Bk1vUxvGHJKMZ9/tA==",
      "transmissionRiskLevel": 3,
      "rollingStartIntervalNumber": 2676672,
      "rollingPeriod": 144
    },
    {
      "keyData": "AXdfnF7CO4lkDKRNSkF8mA==",
      "transmissionRiskLevel": 2,
      "rollingStartIntervalNumber": 2675232,
      "rollingPeriod": 144
    },
    {
      "keyData": "Brt+1e4J5Kvhj4cMlgh52w==",
      "transmissionRiskLevel": 3,
      "rollingStartIntervalNumber": 2675088,
      "rollingPeriod": 144
    },
    {
      "keyData": "CjKHriSqOTdMAs7GpUKzMA==",
      "transmissionRiskLevel": 1,
      "rollingStartIntervalNumber": 2676240,
      "rollingPeriod": 144
    },
    {
      "keyData": "CuVuMNCxVFMcr7Uja7m4ew==",
      "transmissionRiskLevel": 2,
      "rollingStartIntervalNumber": 2676672,
      "rollingPeriod": 144
    },
    {
      "keyData": "DJxswRheZWq0lYlcTy6B1A==",
      "transmissionRiskLevel": 3,
      "rollingStartIntervalNumber": 2674944,
      "rollingPeriod": 144
    },
    {
      "keyData": "EAqFbKcM7ZmvAvfIQZDtgw==",
      "transmissionRiskLevel": 3,
      "rollingStartIntervalNumber": 2674656,
      "rollingPeriod": 144
    },
    {
      "keyData": "FpMX6huAq5dDB7WMcdig1g==",
      "transmissionRiskLevel": 2,
      "rollingStartIntervalNumber": 2676096,
      "rollingPeriod": 144
    },
    {
      "keyData": "GM9ndBsIkMgP7dyVohUNbw==",
      "transmissionRiskLevel": 2,
      "rollingStartIntervalNumber": 2676672,
      "rollingPeriod": 144
    },
    {
      "keyData": "GPV5jmeI8tUWrJjI9tQaxg==",
      "transmissionRiskLevel": 3,
      "rollingStartIntervalNumber": 2676096,
      "rollingPeriod": 144
    },
    {
      "keyData": "GSo0qi4zzpdYqIBBVD7fFA==",
      "transmissionRiskLevel": 1,
      "rollingStartIntervalNumber": 2675808,
      "rollingPeriod": 144
    },
    {
      "keyData": "HBrj/PpJiLUTUIxBPCuMxg==",
      "transmissionRiskLevel": 2,
      "rollingStartIntervalNumber": 2674944,
      "rollingPeriod": 144
    },
    {
      "keyData": "HC5XzOmfotI1xbxNePCl6A==",
      "transmissionRiskLevel": 3,
      "rollingStartIntervalNumber": 2675664,
      "rollingPeriod": 144
    },
    {
      "keyData": "Hk1kXikfMuiUIbAr/ryiHg==",
      "transmissionRiskLevel": 3,
      "rollingStartIntervalNumber": 2676240,
      "rollingPeriod": 144
    },
    {
      "keyData": "HlJD68mf7CMfZCgY9t6Bog==",
      "transmissionRiskLevel": 1,
      "rollingStartIntervalNumber": 2675232,
      "rollingPeriod": 144
    },
    {
      "keyData": "H+Mvpp/fsxvcklkuciDjvA==",
      "transmissionRiskLevel": 1,
      "rollingStartIntervalNumber": 2674656,
      "rollingPeriod": 144
    },
    {
      "keyData": "IAVdFe/VbncwHpYawN8glg==",
      "transmissionRiskLevel": 1,
      "rollingStartIntervalNumber": 2676240,
      "rollingPeriod": 144
    },
    {
      "keyData": "IJbvdfXV4BbHzY+1E9tgeQ==",
      "transmissionRiskLevel": 1,
      "rollingStartIntervalNumber": 2676096,
      "rollingPeriod": 144
    },
    {
      "keyData": "JFZf+kV57dDkCy5QuuuM9g==",
      "transmissionRiskLevel": 2,
      "rollingStartIntervalNumber": 2676096,
      "rollingPeriod": 144
    },
    {
      "keyData": "JrLBKs7iZh9TGEYoinaMVw==",
      "transmissionRiskLevel": 2,
      "rollingStartIntervalNumber": 2675952,
      "rollingPeriod": 144
    },
    {
      "keyData": "K8nbqMxEFbbSLPZ2RkithA==",
      "transmissionRiskLevel": 3,
      "rollingStartIntervalNumber": 2675808,
      "rollingPeriod": 144
    },
    {
      "keyData": "LG4bfnDO0ol1K0+mnmN9Zg==",
      "transmissionRiskLevel": 2,
      "rollingStartIntervalNumber": 2674656,
      "rollingPeriod": 144
    },
    {
      "keyData": "LVbLcNW9frZg16+UrHuN/w==",
      "transmissionRiskLevel": 1,
      "rollingStartIntervalNumber": 2675376,
      "rollingPeriod": 144
    },
    {
      "keyData": "Lhk4/Mw1dtM2L88M1yZe6w==",
      "transmissionRiskLevel": 1,
      "rollingStartIntervalNumber": 2675520,
      "rollingPeriod": 144
    },
    {
      "keyData": "LnGwlwUukUYE5wFCd6IO0Q==",
      "transmissionRiskLevel": 2,
      "rollingStartIntervalNumber": 2675088,
      "rollingPeriod": 144
    },
    {
      "keyData": "MINz9PkmCXm+542WXXB8PQ==",
      "transmissionRiskLevel": 3,
      "rollingStartIntervalNumber": 2675808,
      "rollingPeriod": 144
    },
    {
      "keyData": "MdrVu+UvU5w9EYzpUi4WFg==",
      "transmissionRiskLevel": 3,
      "rollingStartIntervalNumber": 2675232,
      "rollingPeriod": 144
    },
    {
      "keyData": "Mq9rhFiEUL05VcSDbX+LeA==",
      "transmissionRiskLevel": 3,
      "rollingStartIntervalNumber": 2676240,
      "rollingPeriod": 144
    },
    {
      "keyData": "NZ5MEsGR3eojv0ruJ43RCg==",
      "transmissionRiskLevel": 2,
      "rollingStartIntervalNumber": 2675664,
      "rollingPeriod": 144
    },
    {
      "keyData": "NkXmZZaTcQqxDSZftNSYVg==",
      "transmissionRiskLevel": 3,
      "rollingStartIntervalNumber": 2676672,
      "rollingPeriod": 144
    },
    {
      "keyData": "NqeEb3jGuLShQAf+d+04Sw==",
      "transmissionRiskLevel": 2,
      "rollingStartIntervalNumber": 2674944,
      "rollingPeriod": 144
    },
    {
      "keyData": "Ns0fS7H7b4F0cpKuNyhv6A==",
      "transmissionRiskLevel": 1,
      "rollingStartIntervalNumber": 2674656,
      "rollingPeriod": 144
    },
    {
      "keyData": "OUAwIwLTSQ70tF9DVpSt3g==",
      "transmissionRiskLevel": 3,
      "rollingStartIntervalNumber": 2675376,
      "rollingPeriod": 144
    },
    {
      "keyData": "PPVQVT57Rkv8cGdDKHQsRA==",
      "transmissionRiskLevel": 3,
      "rollingStartIntervalNumber": 2676096,
      "rollingPeriod": 144
    },
    {
      "keyData": "PXC/eTgZ29bkO7eHoo+fRg==",
      "transmissionRiskLevel": 1,
      "rollingStartIntervalNumber": 2674944,
      "rollingPeriod": 144
    },
    {
      "keyData": "Pv9Lg36kMr4ggeI0tsZc2w==",
      "transmissionRiskLevel": 2,
      "rollingStartIntervalNumber": 2675952,
      "rollingPeriod": 144
    },
    {
      "keyData": "QDZKMsk3A9iZVrMWCnULqA==",
      "transmissionRiskLevel": 3,
      "rollingStartIntervalNumber": 2676384,
      "rollingPeriod": 144
    },
    {
      "keyData": "RVmzJzSWKk5Rr69TY3TYwA==",
      "transmissionRiskLevel": 3,
      "rollingStartIntervalNumber": 2674944,
      "rollingPeriod": 144
    },
    {
      "keyData": "R5tCA4QFcZ9GBzoo2Z/uYQ==",
      "transmissionRiskLevel": 3,
      "rollingStartIntervalNumber": 2676528,
      "rollingPeriod": 144
    },
    {
      "keyData": "SFWEnQYd+yrp4x/oNXuYRg==",
      "transmissionRiskLevel": 1,
      "rollingStartIntervalNumber": 2675520,
      "rollingPeriod": 144
    },
    {
      "keyData": "VE03jueBOAq7JhQFGlVhzg==",
      "transmissionRiskLevel": 1,
      "rollingStartIntervalNumber": 2676384,
      "rollingPeriod": 144
    },
    {
      "keyData": "VL5oshGd57qsQt8pZsXQNg==",
      "transmissionRiskLevel": 3,
      "rollingStartIntervalNumber": 2676384,
      "rollingPeriod": 144
    },
    {
      "keyData": "VdRq/EFyv2yRty4c8srB9w==",
      "transmissionRiskLevel": 2,
      "rollingStartIntervalNumber": 2674944,
      "rollingPeriod": 144
    },
    {
      "keyData": "WMb0BC+BCcLEQCIgUqevJg==",
      "transmissionRiskLevel": 1,
      "rollingStartIntervalNumber": 2675088,
      "rollingPeriod": 144
    },
    {
      "keyData": "WTSnUI+I+mYptZyjLjnnWA==",
      "transmissionRiskLevel": 2,
      "rollingStartIntervalNumber": 2675232,
      "rollingPeriod": 144
    },
    {
      "keyData": "WeMPTlrG0stt3qBQ/6Pfug==",
      "transmissionRiskLevel": 2,
      "rollingStartIntervalNumber": 2676096,
      "rollingPeriod": 144
    },
    {
      "keyData": "Wjl6+F7fO9qlT/NbVf7JpA==",
      "transmissionRiskLevel": 2,
      "rollingStartIntervalNumber": 2676528,
      "rollingPeriod": 144
    },
    {
      "keyData": "XHRCvSAE+VFfOo/gnY1qfQ==",
      "transmissionRiskLevel": 1,
      "rollingStartIntervalNumber": 2675520,
      "rollingPeriod": 144
    },
    {
      "keyData": "XzGwmvvFonj35s8ci1+E3w==",
      "transmissionRiskLevel": 3,
      "rollingStartIntervalNumber": 2676096,
      "rollingPeriod": 144
    },
    {
      "keyData": "X5TpGbLFLnQfKmDz9/jI0g==",
      "transmissionRiskLevel": 2,
      "rollingStartIntervalNumber": 2675520,
      "rollingPeriod": 144
    },
    {
      "keyData": "YRKgxoCncDLthbCtC4V56A==",
      "transmissionRiskLevel": 3,
      "rollingStartIntervalNumber": 2674656,
      "rollingPeriod": 144
    },
    {
      "keyData": "Y7xG5Nw4NmDz/1OXIhsJmA==",
      "transmissionRiskLevel": 2,
      "rollingStartIntervalNumber": 2676384,
      "rollingPeriod": 144
    },
    {
      "keyData": "ZbXs+Sn7W4JN6O2oSsSQag==",
      "transmissionRiskLevel": 1,
      "rollingStartIntervalNumber": 2676240,
      "rollingPeriod": 144
    },
    {
      "keyData": "Z4uYNOY9eoXkTn12lz/MIg==",
      "transmissionRiskLevel": 1,
      "rollingStartIntervalNumber": 2675232,
      "rollingPeriod": 144
    },
    {
      "keyData": "aBpFjVgrJ/RQ39al4sjF+w==",
      "transmissionRiskLevel": 3,
      "rollingStartIntervalNumber": 2676528,
      "rollingPeriod": 144
    },
    {
      "keyData": "aIbzeT2u/kwUAuCLgBPo0Q==",
      "transmissionRiskLevel": 2,
      "rollingStartIntervalNumber": 2675952,
      "rollingPeriod": 144
    },
    {
      "keyData": "aQAsiWi092eO1aMQ+Ssobg==",
      "transmissionRiskLevel": 1,
      "rollingStartIntervalNumber": 2675952,
      "rollingPeriod": 144
    },
    {
      "keyData": "aUOEPfHwwbueyokDsSCkeQ==",
      "transmissionRiskLevel": 3,
      "rollingStartIntervalNumber": 2676096,
      "rollingPeriod": 144
    },
    {
      "keyData": "bPqq9EvNTOC+5cmXH9H1Og==",
      "transmissionRiskLevel": 2,
      "rollingStartIntervalNumber": 2675232,
      "rollingPeriod": 144
    },
    {
      "keyData": "bT0L+t+E+BSC9HNUyltivA==",
      "transmissionRiskLevel": 3,
      "rollingStartIntervalNumber": 2675664,
      "rollingPeriod": 144
    },
    {
      "keyData": "cDjSAKHvdXb5L3lJsKoUSg==",
      "transmissionRiskLevel": 1,
      "rollingStartIntervalNumber": 2675088,
      "rollingPeriod": 144
    },
    {
      "keyData": "cGRdXjcm/TEVo3AhHgGTIw==",
      "transmissionRiskLevel": 2,
      "rollingStartIntervalNumber": 2674944,
      "rollingPeriod": 144
    },
    {
      "keyData": "cNur4i5GrARTwpSoD+LqxA==",
      "transmissionRiskLevel": 3,
      "rollingStartIntervalNumber": 2675088,
      "rollingPeriod": 144
    },
    {
      "keyData": "cvC3hUjP4Q4P+0jOHtQvng==",
      "transmissionRiskLevel": 1,
      "rollingStartIntervalNumber": 2675664,
      "rollingPeriod": 144
    },
    {
      "keyData": "dH08YThws+59ue2Xem8UQA==",
      "transmissionRiskLevel": 3,
      "rollingStartIntervalNumber": 2676240,
      "rollingPeriod": 144
    },
    {
      "keyData": "ddKJoRDpp3Dj0VhXSArkiQ==",
      "transmissionRiskLevel": 1,
      "rollingStartIntervalNumber": 2676672,
      "rollingPeriod": 144
    },
    {
      "keyData": "dmdnVK1C1L8CKH8jslj5EA==",
      "transmissionRiskLevel": 3,
      "rollingStartIntervalNumber": 2676528,
      "rollingPeriod": 144
    },
    {
      "keyData": "ec6+VNMnVKCW5yTAhkG1Ng==",
      "transmissionRiskLevel": 1,
      "rollingStartIntervalNumber": 2676240,
      "rollingPeriod": 144
    },
    {
      "keyData": "fV8CQ5zXjerzaKsBJbkVIQ==",
      "transmissionRiskLevel": 3,
      "rollingStartIntervalNumber": 2676672,
      "rollingPeriod": 144
    },
    {
      "keyData": "grgQR1nZqmrfHGTC+W+qvQ==",
      "transmissionRiskLevel": 3,
      "rollingStartIntervalNumber": 2674800,
      "rollingPeriod": 144
    },
    {
      "keyData": "gvaDBxjM4mGNviY0jVWYVw==",
      "transmissionRiskLevel": 1,
      "rollingStartIntervalNumber": 2676528,
      "rollingPeriod": 144
    },
    {
      "keyData": "hdUGMMhTkFvuRTb0g2cqJw==",
      "transmissionRiskLevel": 3,
      "rollingStartIntervalNumber": 2674944,
      "rollingPeriod": 144
    },
    {
      "keyData": "ihw3hYy096xTFrfEA8QM0Q==",
      "transmissionRiskLevel": 2,
      "rollingStartIntervalNumber": 2675376,
      "rollingPeriod": 144
    },
    {
      "keyData": "j2dAQwSRrqczkskR1xNBGw==",
      "transmissionRiskLevel": 1,
      "rollingStartIntervalNumber": 2676384,
      "rollingPeriod": 144
    },
    {
      "keyData": "kGcUE8vMAoBrrfWm5bwZWw==",
      "transmissionRiskLevel": 2,
      "rollingStartIntervalNumber": 2675952,
      "rollingPeriod": 144
    },
    {
      "keyData": "kM5aVoDLDGVQrau/06hJxg==",
      "transmissionRiskLevel": 1,
      "rollingStartIntervalNumber": 2674800,
      "rollingPeriod": 144
    },
    {
      "keyData": "kkqAqURFnSm5iZFS67p4bg==",
      "transmissionRiskLevel": 3,
      "rollingStartIntervalNumber": 2675376,
      "rollingPeriod": 144
    },
    {
      "keyData": "lNxQrQ0knTnokSWZMLFaag==",
      "transmissionRiskLevel": 2,
      "rollingStartIntervalNumber": 2675664,
      "rollingPeriod": 144
    },
    {
      "keyData": "la/aX5nCApmVIMSi9VSM/w==",
      "transmissionRiskLevel": 3,
      "rollingStartIntervalNumber": 2675088,
      "rollingPeriod": 144
    },
    {
      "keyData": "lfEAr2v7lkHoTvfaDcJOIQ==",
      "transmissionRiskLevel": 3,
      "rollingStartIntervalNumber": 2676096,
      "rollingPeriod": 144
    },
    {
      "keyData": "mOVO427CB9QY1grKLA0YGQ==",
      "transmissionRiskLevel": 2,
      "rollingStartIntervalNumber": 2676384,
      "rollingPeriod": 144
    },
    {
      "keyData": "mPgD+ENXdlcd4RGyFiHz4g==",
      "transmissionRiskLevel": 2,
      "rollingStartIntervalNumber": 2675808,
      "rollingPeriod": 144
    },
    {
      "keyData": "nvkJcEvSgtR3Dd5xIqupXA==",
      "transmissionRiskLevel": 1,
      "rollingStartIntervalNumber": 2676240,
      "rollingPeriod": 144
    },
    {
      "keyData": "oAp9+XRJ0duWKWfPQB/8dw==",
      "transmissionRiskLevel": 3,
      "rollingStartIntervalNumber": 2674656,
      "rollingPeriod": 144
    },
    {
      "keyData": "ohVCOOHgmJTZrx0gc1FuKQ==",
      "transmissionRiskLevel": 3,
      "rollingStartIntervalNumber": 2675088,
      "rollingPeriod": 144
    },
    {
      "keyData": "ozsA4TML9KiQ4VoaRK0ifQ==",
      "transmissionRiskLevel": 3,
      "rollingStartIntervalNumber": 2675664,
      "rollingPeriod": 144
    },
    {
      "keyData": "pt2qy62lXnB2LtntCs6ymw==",
      "transmissionRiskLevel": 2,
      "rollingStartIntervalNumber": 2675232,
      "rollingPeriod": 144
    },
    {
      "keyData": "py4F0bV9UkgwNzq4jnpvfA==",
      "transmissionRiskLevel": 2,
      "rollingStartIntervalNumber": 2676528,
      "rollingPeriod": 144
    },
    {
      "keyData": "qIUsKK7XkDSGc/mLguctOA==",
      "transmissionRiskLevel": 1,
      "rollingStartIntervalNumber": 2674656,
      "rollingPeriod": 144
    },
    {
      "keyData": "rLhRwAwVyu6r2dlc8xm5dg==",
      "transmissionRiskLevel": 3,
      "rollingStartIntervalNumber": 2675376,
      "rollingPeriod": 144
    },
    {
      "keyData": "rOcpMdq5AveZHx+DLCiTWg==",
      "transmissionRiskLevel": 3,
      "rollingStartIntervalNumber": 2676384,
      "rollingPeriod": 144
    },
    {
      "keyData": "rjRS5i2iI1p7xkqwxn28ZA==",
      "transmissionRiskLevel": 2,
      "rollingStartIntervalNumber": 2675088,
      "rollingPeriod": 144
    },
    {
      "keyData": "rzK/qmurw+Ruh3s8s/o27g==",
      "transmissionRiskLevel": 3,
      "rollingStartIntervalNumber": 2674800,
      "rollingPeriod": 144
    },
    {
      "keyData": "r57hx8YH2WKRTtCNUcClNA==",
      "transmissionRiskLevel": 3,
      "rollingStartIntervalNumber": 2676384,
      "rollingPeriod": 144
    },
    {
      "keyData": "scYkrDitd6ULKZ0CbxOIVA==",
      "transmissionRiskLevel": 1,
      "rollingStartIntervalNumber": 2674800,
      "rollingPeriod": 144
    },
    {
      "keyData": "sfO5cZmlvOeqK9W6Uiu8fw==",
      "transmissionRiskLevel": 3,
      "rollingStartIntervalNumber": 2675808,
      "rollingPeriod": 144
    },
    {
      "keyData": "smQUJ18aD9py170pJ1uSbg==",
      "transmissionRiskLevel": 1,
      "rollingStartIntervalNumber": 2676096,
      "rollingPeriod": 144
    },
    {
      "keyData": "soduVXx4rH0ACkJeLJW1HQ==",
      "transmissionRiskLevel": 3,
      "rollingStartIntervalNumber": 2676240,
      "rollingPeriod": 144
    },
    {
      "keyData": "stV2xTwR0B8dqkyh6GmTRA==",
      "transmissionRiskLevel": 1,
      "rollingStartIntervalNumber": 2675664,
      "rollingPeriod": 144
    },
    {
      "keyData": "s72v7zK8okrfR+YGxXfa0w==",
      "transmissionRiskLevel": 1,
      "rollingStartIntervalNumber": 2676240,
      "rollingPeriod": 144
    },
    {
      "keyData": "taeyN5e+02Z1CV1U47t8TQ==",
      "transmissionRiskLevel": 3,
      "rollingStartIntervalNumber": 2674800,
      "rollingPeriod": 144
    },
    {
      "keyData": "uJTDQ8WU1ZFmLM05UuFHLA==",
      "transmissionRiskLevel": 3,
      "rollingStartIntervalNumber": 2676240,
      "rollingPeriod": 144
    },
    {
      "keyData": "u1E1IqfTbI/1My+hg7rrvA==",
      "transmissionRiskLevel": 1,
      "rollingStartIntervalNumber": 2674800,
      "rollingPeriod": 144
    },
    {
      "keyData": "u5rO/+m5Nc7Sh8+DSLHOgA==",
      "transmissionRiskLevel": 1,
      "rollingStartIntervalNumber": 2675232,
      "rollingPeriod": 144
    },
    {
      "keyData": "vZEEQRhBMyAGhOZERZmgvA==",
      "transmissionRiskLevel": 1,
      "rollingStartIntervalNumber": 2675232,
      "rollingPeriod": 144
    },
    {
      "keyData": "vdD+QfpfAr1L32MxVw18iA==",
      "transmissionRiskLevel": 1,
      "rollingStartIntervalNumber": 2674944,
      "rollingPeriod": 144
    },
    {
      "keyData": "vliri1VKT4nyaBrKLw4sMQ==",
      "transmissionRiskLevel": 1,
      "rollingStartIntervalNumber": 2676528,
      "rollingPeriod": 144
    },
    {
      "keyData": "vv6LaTMgsCNnbAy+rWZUtA==",
      "transmissionRiskLevel": 1,
      "rollingStartIntervalNumber": 2674800,
      "rollingPeriod": 144
    },
    {
      "keyData": "v6BzWI/kEiMQ6SZTwOjmxA==",
      "transmissionRiskLevel": 1,
      "rollingStartIntervalNumber": 2676528,
      "rollingPeriod": 144
    },
    {
      "keyData": "v88McR818vbpMG0X6NOApQ==",
      "transmissionRiskLevel": 2,
      "rollingStartIntervalNumber": 2676528,
      "rollingPeriod": 144
    },
    {
      "keyData": "wRgSlVZ7kb2NZ1Of7UtgYA==",
      "transmissionRiskLevel": 3,
      "rollingStartIntervalNumber": 2675520,
      "rollingPeriod": 144
    },
    {
      "keyData": "wUg/0nEFmGJSg97nIPB2Ug==",
      "transmissionRiskLevel": 1,
      "rollingStartIntervalNumber": 2676096,
      "rollingPeriod": 144
    },
    {
      "keyData": "wnb5Cgtf8KKfB28Rn+Kqgw==",
      "transmissionRiskLevel": 1,
      "rollingStartIntervalNumber": 2675808,
      "rollingPeriod": 144
    },
    {
      "keyData": "w7SGYtJCsIeeN3yLB0BI1Q==",
      "transmissionRiskLevel": 3,
      "rollingStartIntervalNumber": 2674656,
      "rollingPeriod": 144
    },
    {
      "keyData": "xU42YqAn1JrfGzVRL5b1hA==",
      "transmissionRiskLevel": 2,
      "rollingStartIntervalNumber": 2675952,
      "rollingPeriod": 144
    },
    {
      "keyData": "xXoNucxzDjth7fKhYEwFAg==",
      "transmissionRiskLevel": 2,
      "rollingStartIntervalNumber": 2674800,
      "rollingPeriod": 144
    },
    {
      "keyData": "yGpL1xJyyjtVYnwUo3iv/Q==",
      "transmissionRiskLevel": 1,
      "rollingStartIntervalNumber": 2675520,
      "rollingPeriod": 144
    },
    {
      "keyData": "yQEJINK1LI2OXMOSgOxy0A==",
      "transmissionRiskLevel": 1,
      "rollingStartIntervalNumber": 2674656,
      "rollingPeriod": 144
    },
    {
      "keyData": "yXhfWn0Yx9oCgvl9CjKo9w==",
      "transmissionRiskLevel": 3,
      "rollingStartIntervalNumber": 2674800,
      "rollingPeriod": 144
    },
    {
      "keyData": "y+oDvZnnBGEL/+WdQAHbYg==",
      "transmissionRiskLevel": 2,
      "rollingStartIntervalNumber": 2676672,
      "rollingPeriod": 144
    },
    {
      "keyData": "0BVuqVxaUF2960g0S0SQ+Q==",
      "transmissionRiskLevel": 2,
      "rollingStartIntervalNumber": 2676528,
      "rollingPeriod": 144
    },
    {
      "keyData": "0TaazJrkQzuY9nHGV4gs0Q==",
      "transmissionRiskLevel": 3,
      "rollingStartIntervalNumber": 2675088,
      "rollingPeriod": 144
    },
    {
      "keyData": "0XN/yhba3BF3X1wowYGjAA==",
      "transmissionRiskLevel": 2,
      "rollingStartIntervalNumber": 2675952,
      "rollingPeriod": 144
    },
    {
      "keyData": "0tPJtiNZt28jRb3OB/131Q==",
      "transmissionRiskLevel": 2,
      "rollingStartIntervalNumber": 2676528,
      "rollingPeriod": 144
    },
    {
      "keyData": "0zNlvGX9h5eCu1jp545MrQ==",
      "transmissionRiskLevel": 1,
      "rollingStartIntervalNumber": 2675088,
      "rollingPeriod": 144
    },
    {
      "keyData": "1ZA5c8UR1VGKWPYB5SyxaQ==",
      "transmissionRiskLevel": 2,
      "rollingStartIntervalNumber": 2674800,
      "rollingPeriod": 144
    },
    {
      "keyData": "2Sl5EHQh9T5PoiMvUOgfrg==",
      "transmissionRiskLevel": 1,
      "rollingStartIntervalNumber": 2674800,
      "rollingPeriod": 144
    },
    {
      "keyData": "2972mq+TKyAw47rbeuJUUQ==",
      "transmissionRiskLevel": 2,
      "rollingStartIntervalNumber": 2676240,
      "rollingPeriod": 144
    },
    {
      "keyData": "3dQ+Isy4GkYu0wJisIXUdg==",
      "transmissionRiskLevel": 1,
      "rollingStartIntervalNumber": 2675232,
      "rollingPeriod": 144
    },
    {
      "keyData": "3tyFtqzhfRRxLlaWiodGUg==",
      "transmissionRiskLevel": 2,
      "rollingStartIntervalNumber": 2674656,
      "rollingPeriod": 144
    },
    {
      "keyData": "3wj1Y0CQopGZXrkP7HhDLA==",
      "transmissionRiskLevel": 2,
      "rollingStartIntervalNumber": 2675376,
      "rollingPeriod": 144
    },
    {
      "keyData": "4S6v/eDJjnzoX/gzJYwxkg==",
      "transmissionRiskLevel": 2,
      "rollingStartIntervalNumber": 2674656,
      "rollingPeriod": 144
    },
    {
      "keyData": "4XHHLkCmNWsQ+1WkwBP9Nw==",
      "transmissionRiskLevel": 1,
      "rollingStartIntervalNumber": 2676240,
      "rollingPeriod": 144
    },
    {
      "keyData": "4dJYSwFhUo98q9Ln8nSTFQ==",
      "transmissionRiskLevel": 2,
      "rollingStartIntervalNumber": 2676240,
      "rollingPeriod": 144
    },
    {
      "keyData": "4hOKBEgDN+R1qNgJ0IenWQ==",
      "transmissionRiskLevel": 3,
      "rollingStartIntervalNumber": 2675520,
      "rollingPeriod": 144
    },
    {
      "keyData": "5HiS8nVeRmWpR23swf/Lyw==",
      "transmissionRiskLevel": 1,
      "rollingStartIntervalNumber": 2676384,
      "rollingPeriod": 144
    },
    {
      "keyData": "6Kb5qtfRYcu6utwG3xKC3A==",
      "transmissionRiskLevel": 2,
      "rollingStartIntervalNumber": 2676096,
      "rollingPeriod": 144
    },
    {
      "keyData": "6MrYNjkHFwjH8ULyH2yMOg==",
      "transmissionRiskLevel": 1,
      "rollingStartIntervalNumber": 2675376,
      "rollingPeriod": 144
    },
    {
      "keyData": "7NF03Uqwe84YquT3svTwrg==",
      "transmissionRiskLevel": 2,
      "rollingStartIntervalNumber": 2676240,
      "rollingPeriod": 144
    },
    {
      "keyData": "7Tjj1luG402uWTqNXTYFbA==",
      "transmissionRiskLevel": 3,
      "rollingStartIntervalNumber": 2675808,
      "rollingPeriod": 144
    },
    {
      "keyData": "7hrHSg3Wljv2NQTXjDTmNQ==",
      "transmissionRiskLevel": 3,
      "rollingStartIntervalNumber": 2675808,
      "rollingPeriod": 144
    },
    {
      "keyData": "8FqgL+3ERFo0dDMJaaHAdg==",
      "transmissionRiskLevel": 2,
      "rollingStartIntervalNumber": 2675376,
      "rollingPeriod": 144
    },
    {
      "keyData": "8ZQscRXRQ2zXZsjbDGOInw==",
      "transmissionRiskLevel": 2,
      "rollingStartIntervalNumber": 2674800,
      "rollingPeriod": 144
    },
    {
      "keyData": "8jnvtxjQm18nI7nMloOdkw==",
      "transmissionRiskLevel": 1,
      "rollingStartIntervalNumber": 2676384,
      "rollingPeriod": 144
    },
    {
      "keyData": "8k1fjBeRivgm6IXi93Bubw==",
      "transmissionRiskLevel": 3,
      "rollingStartIntervalNumber": 2675088,
      "rollingPeriod": 144
    },
    {
      "keyData": "9BYQa3s2Rq+4ozwoEDff2g==",
      "transmissionRiskLevel": 1,
      "rollingStartIntervalNumber": 2676384,
      "rollingPeriod": 144
    },
    {
      "keyData": "9X0q551d/NiabYzgbaKFQw==",
      "transmissionRiskLevel": 2,
      "rollingStartIntervalNumber": 2675664,
      "rollingPeriod": 144
    },
    {
      "keyData": "91lUUt3UId9mJ3FHWZYVvA==",
      "transmissionRiskLevel": 2,
      "rollingStartIntervalNumber": 2675520,
      "rollingPeriod": 144
    },
    {
      "keyData": "94rWZriUCktbQW/FRxUTTg==",
      "transmissionRiskLevel": 2,
      "rollingStartIntervalNumber": 2676672,
      "rollingPeriod": 144
    },
    {
      "keyData": "/1FFeSDikykX/ECJ0Xie/Q==",
      "transmissionRiskLevel": 3,
      "rollingStartIntervalNumber": 2676672,
      "rollingPeriod": 144
    }
  ]
}