{
  "startTimestamp": "1604606580",
  "endTimestamp": "1604692980",
  "region": "NL",
  "batchNum": 1,
  "batchSize": 1,
  "signatureInfos": [
    {
      "verificationKeyVersion": "v12",
      "verificationKeyId": "204",
      "signatureAlgorithm": "1.2.840.10045.4.3.2"
    }
  ],
  "keys": [
    {
      "keyData": "AHJITHgIjIugS7Q/b702xQ==",
      "transmissionRiskLevel": 2,
      "rollingStartIntervalNumber": 2673792,
      "rollingPeriod": 144
    },
    {
      "keyData": "AL6bAuNhlRS+1VnmCs+DbA==",
      "transmissionRiskLevel": 2,
      "rollingStartIntervalNumber": 2674080,
      "rollingPeriod": 144
    },
    {
      "keyData": "AOOjBdtlGBzkmkwoE8MiLQ==",
      "transmissionRiskLevel": 3,
      "rollingStartIntervalNumber": 2673936,
      "rollingPeriod": 144
    },
    {
      "keyData": "AetJMCwXqKtEt3JI1M5Qpg==",
      "transmissionRiskLevel": 3,
      "rollingStartIntervalNumber": 2673648,
      "rollingPeriod": 144
    },
    {
      "keyData": "COMzt0iTJ81YluHMzFJ/7g==",
      "transmissionRiskLevel": 3,
      "rollingStartIntervalNumber": 2674080,
      "rollingPeriod": 144
    },
    {
      "keyData": "CSvxoMj+JhPJaQj69MFbmA==",
      "transmissionRiskLevel": 1,
      "rollingStartIntervalNumber": 2672640,
      "rollingPeriod": 144
    },
    {
      "keyData": "CzULOJuWgs8l0wd15NqGrQ==",
      "transmissionRiskLevel": 3,
      "rollingStartIntervalNumber": 2673936,
      "rollingPeriod": 144
    },
    {
      "keyData": "DEDdI78D4XpBb4ZKW0rMBQ==",
      "transmissionRiskLevel": 1,
      "rollingStartIntervalNumber": 2672496,
      "rollingPeriod": 144
    },
    {
      "keyData": "Dc+68ZY3jmgg3wWekwmDdg==",
      "transmissionRiskLevel": 3,
      "rollingStartIntervalNumber": 2674080,
      "rollingPeriod": 144
    },
    {
      "keyData": "Dm/LnmJL5hbxKIyZiJuKiQ==",
      "transmissionRiskLevel": 3,
      "rollingStartIntervalNumber": 2673648,
      "rollingPeriod": 144
    },
    {
      "keyData": "D/CpTCXK10Ueon93+b/LoA==",
      "transmissionRiskLevel": 1,
      "rollingStartIntervalNumber": 2672784,
      "rollingPeriod": 144
    },
    {
      "keyData": "EP23E67ekr6RpKxUagadtQ==",
      "transmissionRiskLevel": 3,
      "rollingStartIntervalNumber": 2674224,
      "rollingPeriod": 144
    },
    {
      "keyData": "EVdrabATR/bkkvXoJE5Qqg==",
      "transmissionRiskLevel": 3,
      "rollingStartIntervalNumber": 2673648,
      "rollingPeriod": 144
    },
    {
      "keyData": "FLdiodruXf8zKcx+27Khzw==",
      "transmissionRiskLevel": 2,
      "rollingStartIntervalNumber": 2672496,
      "rollingPeriod": 144
    },
    {
      "keyData": "FWvbqtuCS6NkYaEogn8HAg==",
      "transmissionRiskLevel": 1,
      "rollingStartIntervalNumber": 2672352,
      "rollingPeriod": 144
    },
    {
      "keyData": "FX2jxDtkQNXt1oEzB1fInA==",
      "transmissionRiskLevel": 3,
      "rollingStartIntervalNumber": 2672496,
      "rollingPeriod": 144
    },
    {
      "keyData": "GGsihai7YOLgdI7GhTqdbw==",
      "transmissionRiskLevel": 3,
      "rollingStartIntervalNumber": 2673072,
      "rollingPeriod": 144
    },
    {
      "keyData": "GZ57o9DblnxxUhEzpEt3Qg==",
      "transmissionRiskLevel": 3,
      "rollingStartIntervalNumber": 2674080,
      "rollingPeriod": 144
    },
    {
      "keyData": "GlK2By4Rd/LBvIf0MJBsHg==",
      "transmissionRiskLevel": 2,
      "rollingStartIntervalNumber": 2673936,
      "rollingPeriod": 144
    },
    {
      "keyData": "Hc8QQB4yt3rxpYzgVUI6fg==",
      "transmissionRiskLevel": 2,
      "rollingStartIntervalNumber": 2672784,
      "rollingPeriod": 144
    },
    {
      "keyData": "Iq1j7pmPE6D/9qKNJLOPZA==",
      "transmissionRiskLevel": 3,
      "rollingStartIntervalNumber": 2674080,
      "rollingPeriod": 144
    },
    {
      "keyData": "JPhFM+26x6m1/2z3xoAtAg==",
      "transmissionRiskLevel": 2,
      "rollingStartIntervalNumber": 2672928,
      "rollingPeriod": 144
    },
    {
      "keyData": "JXRT8OUjVtvmXi8X2KsJyg==",
      "transmissionRiskLevel": 3,
      "rollingStartIntervalNumber": 2672352,
      "rollingPeriod": 144
    },
    {
      "keyData": "JmbCjSit3Ar9ELaYW/pnsg==",
      "transmissionRiskLevel": 2,
      "rollingStartIntervalNumber": 2672352,
      "rollingPeriod": 144
    },
    {
      "keyData": "JwXjblTWOBDNxgUK9CO7OA==",
      "transmissionRiskLevel": 1,
      "rollingStartIntervalNumber": 2672640,
      "rollingPeriod": 144
    },
    {
      "keyData": "KZFjLUkmLHKbapH+Rn7aYQ==",
      "transmissionRiskLevel": 3,
      "rollingStartIntervalNumber": 2673936,
      "rollingPeriod": 144
    },
    {
      "keyData": "LdRYu8gWv/Ki5UR2xl7KsA==",
      "transmissionRiskLevel": 3,
      "rollingStartIntervalNumber": 2673792,
      "rollingPeriod": 144
    },
    {
      "keyData": "LnzHyUaN0AKGnjYoCuI5Qw==",
      "transmissionRiskLevel": 3,
      "rollingStartIntervalNumber": 2674080,
      "rollingPeriod": 144
    },
    {
      "keyData": "MPP7dvQAn4Hgiok1abYJXg==",
      "transmissionRiskLevel": 3,
      "rollingStartIntervalNumber": 2674368,
      "rollingPeriod": 144
    },
    {
      "keyData": "MQevfJ+oEuiymv894tXF1g==",
      "transmissionRiskLevel": 1,
      "rollingStartIntervalNumber": 2673936,
      "rollingPeriod": 144
    },
    {
      "keyData": "MVQI2idMtYl6IYQsKPh3bQ==",
      "transmissionRiskLevel": 3,
      "rollingStartIntervalNumber": 2673792,
      "rollingPeriod": 144
    },
    {
      "keyData": "MvULQk99fNkG3eQ+wrnBKw==",
      "transmissionRiskLevel": 3,
      "rollingStartIntervalNumber": 2674080,
      "rollingPeriod": 144
    },
    {
      "keyData": "NEy+8TWCY/eg7JB+nK0tiA==",
      "transmissionRiskLevel": 3,
      "rollingStartIntervalNumber": 2673936,
      "rollingPeriod": 144
    },
    {
      "keyData": "NTNbLT7VJYhmQew5LOUnCg==",
      "transmissionRiskLevel": 3,
      "rollingStartIntervalNumber": 2673792,
      "rollingPeriod": 144
    },
    {
      "keyData": "NdM/geUHPNAoF9fpYkzpSQ==",
      "transmissionRiskLevel": 3,
      "rollingStartIntervalNumber": 2673360,
      "rollingPeriod": 144
    },
    {
      "keyData": "ONHq7niI8UlFBDug5H9dpA==",
      "transmissionRiskLevel": 3,
      "rollingStartIntervalNumber": 2673792,
      "rollingPeriod": 144
    },
    {
      "keyData": "Oo02wo4u6+trFNhRAc7A1w==",
      "transmissionRiskLevel": 2,
      "rollingStartIntervalNumber": 2673936,
      "rollingPeriod": 144
    },
    {
      "keyData": "O9uj6Spjmec2liirezrQWQ==",
      "transmissionRiskLevel": 1,
      "rollingStartIntervalNumber": 2674224,
      "rollingPeriod": 144
    },
    {
      "keyData": "PdfodvmpB5pWX9R1S+ZroA==",
      "transmissionRiskLevel": 2,
      "rollingStartIntervalNumber": 2673504,
      "rollingPeriod": 144
    },
    {
      "keyData": "QC9btELcHOlHZSc1CCY0tw==",
      "transmissionRiskLevel": 2,
      "rollingStartIntervalNumber": 2673216,
      "rollingPeriod": 144
    },
    {
      "keyData": "QExJVMkENT+bEGEHlTOwbQ==",
      "transmissionRiskLevel": 3,
      "rollingStartIntervalNumber": 2673360,
      "rollingPeriod": 144
    },
    {
      "keyData": "QoQdbHSElZtg/tsHIDo62A==",
      "transmissionRiskLevel": 3,
      "rollingStartIntervalNumber": 2674080,
      "rollingPeriod": 144
    },
    {
      "keyData": "QyYuLL3MlQhR9V8Za8O8yw==",
      "transmissionRiskLevel": 2,
      "rollingStartIntervalNumber": 2673648,
      "rollingPeriod": 144
    },
    {
      "keyData": "Q5r+SYvh/+tm0MQJjG/BIw==",
      "transmissionRiskLevel": 2,
      "rollingStartIntervalNumber": 2673792,
      "rollingPeriod": 144
    },
    {
      "keyData": "RAZSmuNdodlCip/FCA9kMw==",
      "transmissionRiskLevel": 1,
      "rollingStartIntervalNumber": 2672928,
      "rollingPeriod": 144
    },
    {
      "keyData": "RDJsFa6XPR/BlU+fRLlXNw==",
      "transmissionRiskLevel": 2,
      "rollingStartIntervalNumber": 2674080,
      "rollingPeriod": 144
    },
    {
      "keyData": "RN5Dg/BBfrpo2ox90KBYig==",
      "transmissionRiskLevel": 2,
      "rollingStartIntervalNumber": 2672496,
      "rollingPeriod": 144
    },
    {
      "keyData": "RUSfBkAXIH5tGidXUvH2sw==",
      "transmissionRiskLevel": 3,
      "rollingStartIntervalNumber": 2673792,
      "rollingPeriod": 144
    },
    {
      "keyData": "RVaTZEoV8UvsrMo+9s1cwQ==",
      "transmissionRiskLevel": 1,
      "rollingStartIntervalNumber": 2673648,
      "rollingPeriod": 144
    },
    {
      "keyData": "RZPSq70b6wvxwuGdAG5NJw==",
      "transmissionRiskLevel": 1,
      "rollingStartIntervalNumber": 2673792,
      "rollingPeriod": 144
    },
    {
      "keyData": "RtrcjTFTl37nW7njqATNiQ==",
      "transmissionRiskLevel": 2,
      "rollingStartIntervalNumber": 2673648,
      "rollingPeriod": 144
    },
    {
      "keyData": "SGARBW1WLNnsuZ1xOmJMLg==",
      "transmissionRiskLevel": 1,
      "rollingStartIntervalNumber": 2672352,
      "rollingPeriod": 144
    },
    {
      "keyData": "SN7GwcwU2FBhAc0QC6aYpg==",
      "transmissionRiskLevel": 2,
      "rollingStartIntervalNumber": 2674368,
      "rollingPeriod": 144
    },
    {
      "keyData": "SSo1MswpRB7IC4HN+fsMuQ==",
      "transmissionRiskLevel": 1,
      "rollingStartIntervalNumber": 2674224,
      "rollingPeriod": 144
    },
    {
      "keyData": "SbjDv4IKeNkZZ7NyhViZxw==",
      "transmissionRiskLevel": 3,
      "rollingStartIntervalNumber": 2674368,
      "rollingPeriod": 144
    },
    {
      "keyData": "ScBxSVtY4pP+l9m2ndifdQ==",
      "transmissionRiskLevel": 1,
      "rollingStartIntervalNumber": 2673072,
      "rollingPeriod": 144
    },
    {
      "keyData": "TIEAb0BUo/7LY+iS6hEeQw==",
      "transmissionRiskLevel": 2,
      "rollingStartIntervalNumber": 2673072,
      "rollingPeriod": 144
    },
    {
      "keyData": "UowjlVuZUrU93n2saS6E9Q==",
      "transmissionRiskLevel": 1,
      "rollingStartIntervalNumber": 2673216,
      "rollingPeriod": 144
    },
    {
      "keyData": "VBUsC1hMvdvOxIVu9er/Vw==",
      "transmissionRiskLevel": 3,
      "rollingStartIntervalNumber": 2674224,
      "rollingPeriod": 144
    },
    {
      "keyData": "VHacS6Fp5rdBcConQ0biYQ==",
      "transmissionRiskLevel": 3,
      "rollingStartIntervalNumber": 2674224,
      "rollingPeriod": 144
    },
    {
      "keyData": "VyIjip4xFTudVSTlu0fiZg==",
      "transmissionRiskLevel": 3,
      "rollingStartIntervalNumber": 2673216,
      "rollingPeriod": 144
    },
    {
      "keyData": "WDHPvuz9ydgoSDFEodE+kA==",
      "transmissionRiskLevel": 3,
      "rollingStartIntervalNumber": 2673504,
      "rollingPeriod": 144
    },
    {
      "keyData": "W4lLEOxEI51/8r9CM5Y+SA==",
      "transmissionRiskLevel": 2,
      "rollingStartIntervalNumber": 2673648,
      "rollingPeriod": 144
    },
    {
      "keyData": "X28dZjEMbo/wzO0JblNIKg==",
      "transmissionRiskLevel": 1,
      "rollingStartIntervalNumber": 2672496,
      "rollingPeriod": 144
    },
    {
      "keyData": "YdJ6HzzY4zKUhIkJnb4xrQ==",
      "transmissionRiskLevel": 2,
      "rollingStartIntervalNumber": 2673936,
      "rollingPeriod": 144
    },
    {
      "keyData": "YjFViOTJmZQO4Z5t2WKgRA==",
      "transmissionRiskLevel": 1,
      "rollingStartIntervalNumber": 2672928,
      "rollingPeriod": 144
    },
    {
      "keyData": "YqcLFXkW+Zeqf+uF1KhjzQ==",
      "transmissionRiskLevel": 1,
      "rollingStartIntervalNumber": 2672784,
      "rollingPeriod": 144
    },
    {
      "keyData": "YrZmeeQiRkzXTeBz2XPtxg==",
      "transmissionRiskLevel": 2,
      "rollingStartIntervalNumber": 2673360,
      "rollingPeriod": 144
    },
    {
      "keyData": "aZ5dOOMLV3rvLQiUixmfWw==",
      "transmissionRiskLevel": 1,
      "rollingStartIntervalNumber": 2672784,
      "rollingPeriod": 144
    },
    {
      "keyData": "a6bEk4E3Ck31dSysEZRhRA==",
      "transmissionRiskLevel": 2,
      "rollingStartIntervalNumber": 2673936,
      "rollingPeriod": 144
    },
    {
      "keyData": "bP8mkzp1Gu+8bCmoasNGYg==",
      "transmissionRiskLevel": 1,
      "rollingStartIntervalNumber": 2673936,
      "rollingPeriod": 144
    },
    {
      "keyData": "bXNe9aCZRgrJfpWweWL1RA==",
      "transmissionRiskLevel": 3,
      "rollingStartIntervalNumber": 2673936,
      "rollingPeriod": 144
    },
    {
      "keyData": "biIZ2Hh/lQjth379QDshOw==",
      "transmissionRiskLevel": 3,
      "rollingStartIntervalNumber": 2673360,
      "rollingPeriod": 144
    },
    {
      "keyData": "bj5V07/WZZfiEXPObkjZyQ==",
      "transmissionRiskLevel": 2,
      "rollingStartIntervalNumber": 2672928,
      "rollingPeriod": 144
    },
    {
      "keyData": "csnkvBj8ZhzyXDxkPas0Og==",
      "transmissionRiskLevel": 3,
      "rollingStartIntervalNumber": 2674080,
      "rollingPeriod": 144
    },
    {
      "keyData": "cxGVIT8NfH0w42LSwF8xGQ==",
      "transmissionRiskLevel": 1,
      "rollingStartIntervalNumber": 2673792,
      "rollingPeriod": 144
    },
    {
      "keyData": "cy4/3AtuRHf0HjBzWcblhw==",
      "transmissionRiskLevel": 2,
      "rollingStartIntervalNumber": 2672352,
      "rollingPeriod": 144
    },
    {
      "keyData": "ddIzVtA//8h3t8ThlMPKhQ==",
      "transmissionRiskLevel": 3,
      "rollingStartIntervalNumber": 2673936,
      "rollingPeriod": 144
    },
    {
      "keyData": "dkX1QP8fhxVJTA6DOxRakw==",
      "transmissionRiskLevel": 2,
      "rollingStartIntervalNumber": 2672640,
      "rollingPeriod": 144
    },
    {
      "keyData": "d5KztYdpdon9ybVTpRj5xw==",
      "transmissionRiskLevel": 2,
      "rollingStartIntervalNumber": 2673216,
      "rollingPeriod": 144
    },
    {
      "keyData": "d7rrFIlmDyaxA1QYQMa28A==",
      "transmissionRiskLevel": 3,
      "rollingStartIntervalNumber": 2673216,
      "rollingPeriod": 144
    },
    {
      "keyData": "fKvU3vjPS7U4Ibe2krXSFw==",
      "transmissionRiskLevel": 3,
      "rollingStartIntervalNumber": 2673072,
      "rollingPeriod": 144
    },
    {
      "keyData": "fr8sjcUs9H4uG/yfPFXi8A==",
      "transmissionRiskLevel": 3,
      "rollingStartIntervalNumber": 2673504,
      "rollingPeriod": 144
    },
    {
      "keyData": "gXWUrRsU3VEb5+BAOBSutA==",
      "transmissionRiskLevel": 1,
      "rollingStartIntervalNumber": 2672352,
      "rollingPeriod": 144
    },
    {
      "keyData": "g7jn5BIzw3P0aLPYbBRE4w==",
      "transmissionRiskLevel": 1,
      "rollingStartIntervalNumber": 2672928,
      "rollingPeriod": 144
    },
    {
      "keyData": "hP9hld8wpN0jWHKexZmK0Q==",
      "transmissionRiskLevel": 1,
      "rollingStartIntervalNumber": 2672352,
      "rollingPeriod": 144
    },
    {
      "keyData": "hjy48lQtZKpd6Rr0/g3Zfg==",
      "transmissionRiskLevel": 1,
      "rollingStartIntervalNumber": 2672352,
      "rollingPeriod": 144
    },
    {
      "keyData": "h39Ya/skWUBwQtpZW27jBw==",
      "transmissionRiskLevel": 2,
      "rollingStartIntervalNumber": 2672496,
      "rollingPeriod": 144
    },
    {
      "keyData": "i3cz1idysjhwYOC/Aw346A==",
      "transmissionRiskLevel": 2,
      "rollingStartIntervalNumber": 2674080,
      "rollingPeriod": 144
    },
    {
      "keyData": "jeEaWWDcirSQgxuUEak0oQ==",
      "transmissionRiskLevel": 1,
      "rollingStartIntervalNumber": 2674224,
      "rollingPeriod": 144
    },
    {
      "keyData": "ji5OLCqB8Lmd+0T07Ov9dw==",
      "transmissionRiskLevel": 3,
      "rollingStartIntervalNumber": 2674224,
      "rollingPeriod": 144
    },
    {
      "keyData": "j0MU76GctqbIm03pQYhZqQ==",
      "transmissionRiskLevel": 1,
      "rollingStartIntervalNumber": 2673504,
      "rollingPeriod": 144
    },
    {
      "keyData": "kzQSZWS6dWrOyzXDT0cUXQ==",
      "transmissionRiskLevel": 2,
      "rollingStartIntervalNumber": 2673792,
      "rollingPeriod": 144
    },
    {
      "keyData": "k+YWORvXV+VdLJyCX9HsIQ==",
      "transmissionRiskLevel": 2,
      "rollingStartIntervalNumber": 2672496,
      "rollingPeriod": 144
    },
    {
      "keyData": "l8zq60jLZBe/hpZLd+aL9Q==",
      "transmissionRiskLevel": 2,
      "rollingStartIntervalNumber": 2674368,
      "rollingPeriod": 144
    },
    {
      "keyData": "mKaEMiP+0hlZBkoRqDQc1g==",
      "transmissionRiskLevel": 3,
      "rollingStartIntervalNumber": 2674224,
      "rollingPeriod": 144
    },
    {
      "keyData": "moJn6qtmbYho5DpjHvIRxg==",
      "transmissionRiskLevel": 3,
      "rollingStartIntervalNumber": 2674080,
      "rollingPeriod": 144
    },
    {
      "keyData": "m4iiEjK7sDwOxMgOUnqIag==",
      "transmissionRiskLevel": 2,
      "rollingStartIntervalNumber": 2673648,
      "rollingPeriod": 144
    },
    {
      "keyData": "nS0lNd1Xhd+MI0hVAGAjPw==",
      "transmissionRiskLevel": 2,
      "rollingStartIntervalNumber": 2672784,
      "rollingPeriod": 144
    },
    {
      "keyData": "nopBpqGMFol1Mo1VNtXCww==",
      "transmissionRiskLevel": 3,
      "rollingStartIntervalNumber": 2672352,
      "rollingPeriod": 144
    },
    {
      "keyData": "pA4IeTLz5QlKv04L3htZvA==",
      "transmissionRiskLevel": 3,
      "rollingStartIntervalNumber": 2672640,
      "rollingPeriod": 144
    },
    {
      "keyData": "pHsTFc8nHIpUP6K9aTM8Pw==",
      "transmissionRiskLevel": 2,
      "rollingStartIntervalNumber": 2674368,
      "rollingPeriod": 144
    },
    {
      "keyData": "pUwrPVSCgAHK2T2Bp8WwQw==",
      "transmissionRiskLevel": 2,
      "rollingStartIntervalNumber": 2673072,
      "rollingPeriod": 144
    },
    {
      "keyData": "pbFgnp48k8+bFcUDg3zaDA==",
      "transmissionRiskLevel": 2,
      "rollingStartIntervalNumber": 2673792,
      "rollingPeriod": 144
    },
    {
      "keyData": "ph25nRhgHKKZ42l44HAwRA==",
      "transmissionRiskLevel": 1,
      "rollingStartIntervalNumber": 2673360,
      "rollingPeriod": 144
    },
    {
      "keyData": "qgzafNMuX/Zc0dttWdyYzw==",
      "transmissionRiskLevel": 2,
      "rollingStartIntervalNumber": 2672496,
      "rollingPeriod": 144
    },
    {
      "keyData": "qmpSd8WogItoDgJJ07bqww==",
      "transmissionRiskLevel": 1,
      "rollingStartIntervalNumber": 2672352,
      "rollingPeriod": 144
    },
    {
      "keyData": "sqH6i/6tMlf/bQMgTxBKbQ==",
      "transmissionRiskLevel": 3,
      "rollingStartIntervalNumber": 2673936,
      "rollingPeriod": 144
    },
    {
      "keyData": "tFljPSlzzNQUVtZOUqi2pA==",
      "transmissionRiskLevel": 3,
      "rollingStartIntervalNumber": 2673936,
      "rollingPeriod": 144
    },
    {
      "keyData": "tVGD55NI+I0YIuqATbXVgg==",
      "transmissionRiskLevel": 1,
      "rollingStartIntervalNumber": 2674224,
      "rollingPeriod": 144
    },
    {
      "keyData": "uNeDtuD7oXzr8BzsMvnylg==",
      "transmissionRiskLevel": 3,
      "rollingStartIntervalNumber": 2674224,
      "rollingPeriod": 144
    },
    {
      "keyData": "uSFiHFl7tq/BdTsKwCIRYA==",
      "transmissionRiskLevel": 2,
      "rollingStartIntervalNumber": 2674224,
      "rollingPeriod": 144
    },
    {
      "keyData": "uou+CYRKxCWLh1zcWqiugg==",
      "transmissionRiskLevel": 2,
      "rollingStartIntervalNumber": 2672928,
      "rollingPeriod": 144
    },
    {
      "keyData": "u7Twg6qR6cNGrJe2DO82YA==",
      "transmissionRiskLevel": 3,
      "rollingStartIntervalNumber": 2673504,
      "rollingPeriod": 144
    },
    {
      "keyData": "vO3vtS4/scwgX/m2hkOEQQ==",
      "transmissionRiskLevel": 3,
      "rollingStartIntervalNumber": 2674368,
      "rollingPeriod": 144
    },
    {
      "keyData": "vn9IS2pBVs5p31/0B58Meg==",
      "transmissionRiskLevel": 1,
      "rollingStartIntervalNumber": 2674368,
      "rollingPeriod": 144
    },
    {
      "keyData": "wN8IvCbxSc4RAagSFFZ7+w==",
      "transmissionRiskLevel": 3,
      "rollingStartIntervalNumber": 2674224,
      "rollingPeriod": 144
    },
    {
      "keyData": "wYHbKDPyMgPyaBGvjreVwA==",
      "transmissionRiskLevel": 2,
      "rollingStartIntervalNumber": 2673936,
      "rollingPeriod": 144
    },
    {
      "keyData": "wZ19IIRD152pX/m95Ad7wg==",
      "transmissionRiskLevel": 2,
      "rollingStartIntervalNumber": 2674224,
      "rollingPeriod": 144
    },
    {
      "keyData": "w+ZVBxmuz8rKQ5qVfhS9WA==",
      "transmissionRiskLevel": 3,
      "rollingStartIntervalNumber": 2672784,
      "rollingPeriod": 144
    },
    {
      "keyData": "xFdVM6r9jqz+8IIxoq09Kg==",
      "transmissionRiskLevel": 3,
      "rollingStartIntervalNumber": 2672496,
      "rollingPeriod": 144
    },
    {
      "keyData": "xbi9UGdf/k9Sfl0Di9JVFw==",
      "transmissionRiskLevel": 1,
      "rollingStartIntervalNumber": 2672640,
      "rollingPeriod": 144
    },
    {
      "keyData": "yRQQJmy8tBN0sXJth6LuVQ==",
      "transmissionRiskLevel": 3,
      "rollingStartIntervalNumber": 2673792,
      "rollingPeriod": 144
    },
    {
      "keyData": "ykdSxuk3AQ4bOWf3OCaAjQ==",
      "transmissionRiskLevel": 2,
      "rollingStartIntervalNumber": 2672784,
      "rollingPeriod": 144
    },
    {
      "keyData": "y+Xa1vRMn1JAcknMy2DERw==",
      "transmissionRiskLevel": 2,
      "rollingStartIntervalNumber": 2672640,
      "rollingPeriod": 144
    },
    {
      "keyData": "zTNB6CHII18QiWEAz1hFlw==",
      "transmissionRiskLevel": 3,
      "rollingStartIntervalNumber": 2673648,
      "rollingPeriod": 144
    },
    {
      "keyData": "zdYOMLujZiQ5WcyAN/wlgw==",
      "transmissionRiskLevel": 1,
      "rollingStartIntervalNumber": 2672352,
      "rollingPeriod": 144
    },
    {
      "keyData": "z1lFFcsG/wCSylv1J8ioyA==",
      "transmissionRiskLevel": 3,
      "rollingStartIntervalNumber": 2674224,
      "rollingPeriod": 144
    },
    {
      "keyData": "z22kRLVq9QjmsRIJaHaKtw==",
      "transmissionRiskLevel": 3,
      "rollingStartIntervalNumber": 2673936,
      "rollingPeriod": 144
    },
    {
      "keyData": "0+OYzvyuYNSiT09AWd+Ttw==",
      "transmissionRiskLevel": 3,
      "rollingStartIntervalNumber": 2673936,
      "rollingPeriod": 144
    },
    {
      "keyData": "1pexDyAjXSkCk/fCc8Mcpw==",
      "transmissionRiskLevel": 3,
      "rollingStartIntervalNumber": 2673936,
      "rollingPeriod": 144
    },
    {
      "keyData": "2bjV6XcHotnkcgYoTFx6EA==",
      "transmissionRiskLevel": 2,
      "rollingStartIntervalNumber": 2673648,
      "rollingPeriod": 144
    },
    {
      "keyData": "2e01wjg3ZeBzkZatobo8BQ==",
      "transmissionRiskLevel": 3,
      "rollingStartIntervalNumber": 2673936,
      "rollingPeriod": 144
    },
    {
      "keyData": "2mMqdlsPiGfkaUY+wXeGIg==",
      "transmissionRiskLevel": 1,
      "rollingStartIntervalNumber": 2673936,
      "rollingPeriod": 144
    },
    {
      "keyData": "2r7D/LuEgfsDZHfNI/Uxnw==",
      "transmissionRiskLevel": 2,
      "rollingStartIntervalNumber": 2672640,
      "rollingPeriod": 144
    },
    {
      "keyData": "3IanPdiw5yC9mNYEhI7n6g==",
      "transmissionRiskLevel": 3,
      "rollingStartIntervalNumber": 2672928,
      "rollingPeriod": 144
    },
    {
      "keyData": "3hSy1WYzGmzwzhmmY++LVg==",
      "transmissionRiskLevel": 3,
      "rollingStartIntervalNumber": 2672784,
      "rollingPeriod": 144
    },
    {
      "keyData": "5OcRMjX0cH5GM67hAbf9RA==",
      "transmissionRiskLevel": 2,
      "rollingStartIntervalNumber": 2674080,
      "rollingPeriod": 144
    },
    {
      "keyData": "50N+pgxPlbpNQd/soPcnXg==",
      "transmissionRiskLevel": 1,
      "rollingStartIntervalNumber": 2673792,
      "rollingPeriod": 144
    },
    {
      "keyData": "6R0YnkD02rVc7Jvf5KzHAw==",
      "transmissionRiskLevel": 2,
      "rollingStartIntervalNumber": 2672352,
      "rollingPeriod": 144
    },
    {
      "keyData": "6dpRMhJ9K7Voy+7FXDggTw==",
      "transmissionRiskLevel": 2,
      "rollingStartIntervalNumber": 2673648,
      "rollingPeriod": 144
    },
    {
      "keyData": "7ANFCD5wIhdsrk2czrAf5w==",
      "transmissionRiskLevel": 3,
      "rollingStartIntervalNumber": 2674080,
      "rollingPeriod": 144
    },
    {
      "keyData": "7sUA/xre+gTTFisdZQ3pwQ==",
      "transmissionRiskLevel": 3,
      "rollingStartIntervalNumber": 2673216,
      "rollingPeriod": 144
    },
    {
      "keyData": "8Cx3fThTmcis431uu765rA==",
      "transmissionRiskLevel": 1,
      "rollingStartIntervalNumber": 2673792,
      "rollingPeriod": 144
    },
    {
      "keyData": "8LLsTiITZxdAqRdp9a38Vg==",
      "transmissionRiskLevel": 2,
      "rollingStartIntervalNumber": 2674368,
      "rollingPeriod": 144
    },
    {
      "keyData": "9G3UAW4ZpGn6oJa+03dz9w==",
      "transmissionRiskLevel": 3,
      "rollingStartIntervalNumber": 2673792,
      "rollingPeriod": 144
    },
    {
      "keyData": "9Nm6zVkqnIZMiK397A4Stw==",
      "transmissionRiskLevel": 3,
      "rollingStartIntervalNumber": 2674080,
      "rollingPeriod": 144
    },
    {
      "keyData": "9zkdLdkwb6UBVcH1n5ghNg==",
      "transmissionRiskLevel": 3,
      "rollingStartIntervalNumber": 2672352,
      "rollingPeriod": 144
    },
    {
      "keyData": "+Zgs0K5yRTzZ5a9fb6KajQ==",
      "transmissionRiskLevel": 1,
      "rollingStartIntervalNumber": 2673072,
      "rollingPeriod": 144
    },
    {
      "keyData": "/3EQ+9CET4U46/zCihYTfA==",
      "transmissionRiskLevel": 2,
      "rollingStartIntervalNumber": 2672640,
      "rollingPeriod": 144
    }
  ]
}